{
  "參選人": [
    {
      "姓名": "李順涼",
      "政黨": "民主進步黨"
    },
    {
      "姓名": "顏清標",
      "政黨": "無黨團結聯盟"
    }
  ],
  "資料": [
    {
      "區別": "沙鹿區",
      "里別": "居仁里",
      "投票所": 180,
      "有效票數": 983,
      "無效票數": 30,
      "投票數": 1013,
      "已領未投票數": 0,
      "發出票數": 1013,
      "用餘票數": 294,
      "選舉人數": 1307,
      "投票率": 77.51000213623047,
      "李順涼": 421,
      "顏清標": 562
    },
    {
      "區別": "沙鹿區",
      "里別": "洛泉里",
      "投票所": 181,
      "有效票數": 641,
      "無效票數": 33,
      "投票數": 674,
      "已領未投票數": 0,
      "發出票數": 674,
      "用餘票數": 225,
      "選舉人數": 899,
      "投票率": 74.97000122070312,
      "李順涼": 260,
      "顏清標": 381
    },
    {
      "區別": "沙鹿區",
      "里別": "洛泉里",
      "投票所": 182,
      "有效票數": 865,
      "無效票數": 61,
      "投票數": 926,
      "已領未投票數": 0,
      "發出票數": 926,
      "用餘票數": 213,
      "選舉人數": 1139,
      "投票率": 81.30000305175781,
      "李順涼": 349,
      "顏清標": 516
    },
    {
      "區別": "沙鹿區",
      "里別": "沙鹿里",
      "投票所": 183,
      "有效票數": 717,
      "無效票數": 41,
      "投票數": 758,
      "已領未投票數": 0,
      "發出票數": 758,
      "用餘票數": 218,
      "選舉人數": 976,
      "投票率": 77.66000366210938,
      "李順涼": 353,
      "顏清標": 364
    },
    {
      "區別": "沙鹿區",
      "里別": "美仁里",
      "投票所": 184,
      "有效票數": 444,
      "無效票數": 18,
      "投票數": 462,
      "已領未投票數": 0,
      "發出票數": 462,
      "用餘票數": 102,
      "選舉人數": 564,
      "投票率": 81.91000366210938,
      "李順涼": 137,
      "顏清標": 307
    },
    {
      "區別": "沙鹿區",
      "里別": "興仁里",
      "投票所": 185,
      "有效票數": 889,
      "無效票數": 40,
      "投票數": 929,
      "已領未投票數": 0,
      "發出票數": 929,
      "用餘票數": 277,
      "選舉人數": 1206,
      "投票率": 77.02999877929688,
      "李順涼": 337,
      "顏清標": 552
    },
    {
      "區別": "沙鹿區",
      "里別": "興仁里",
      "投票所": 186,
      "有效票數": 779,
      "無效票數": 30,
      "投票數": 809,
      "已領未投票數": 0,
      "發出票數": 809,
      "用餘票數": 241,
      "選舉人數": 1050,
      "投票率": 77.05000305175781,
      "李順涼": 325,
      "顏清標": 454
    },
    {
      "區別": "沙鹿區",
      "里別": "興安里",
      "投票所": 187,
      "有效票數": 1036,
      "無效票數": 48,
      "投票數": 1084,
      "已領未投票數": 0,
      "發出票數": 1084,
      "用餘票數": 322,
      "選舉人數": 1406,
      "投票率": 77.0999984741211,
      "李順涼": 401,
      "顏清標": 635
    },
    {
      "區別": "沙鹿區",
      "里別": "興安里",
      "投票所": 188,
      "有效票數": 1118,
      "無效票數": 56,
      "投票數": 1174,
      "已領未投票數": 0,
      "發出票數": 1174,
      "用餘票數": 375,
      "選舉人數": 1549,
      "投票率": 75.79000091552734,
      "李順涼": 480,
      "顏清標": 638
    },
    {
      "區別": "沙鹿區",
      "里別": "斗抵里",
      "投票所": 189,
      "有效票數": 926,
      "無效票數": 32,
      "投票數": 958,
      "已領未投票數": 0,
      "發出票數": 958,
      "用餘票數": 293,
      "選舉人數": 1251,
      "投票率": 76.58000183105469,
      "李順涼": 328,
      "顏清標": 598
    },
    {
      "區別": "沙鹿區",
      "里別": "斗抵里",
      "投票所": 190,
      "有效票數": 989,
      "無效票數": 45,
      "投票數": 1034,
      "已領未投票數": 0,
      "發出票數": 1034,
      "用餘票數": 296,
      "選舉人數": 1330,
      "投票率": 77.73999786376953,
      "李順涼": 427,
      "顏清標": 562
    },
    {
      "區別": "沙鹿區",
      "里別": "斗抵里",
      "投票所": 191,
      "有效票數": 995,
      "無效票數": 39,
      "投票數": 1034,
      "已領未投票數": 0,
      "發出票數": 1034,
      "用餘票數": 295,
      "選舉人數": 1329,
      "投票率": 77.80000305175781,
      "李順涼": 391,
      "顏清標": 604
    },
    {
      "區別": "沙鹿區",
      "里別": "鹿峰里",
      "投票所": 192,
      "有效票數": 966,
      "無效票數": 51,
      "投票數": 1017,
      "已領未投票數": 0,
      "發出票數": 1017,
      "用餘票數": 348,
      "選舉人數": 1365,
      "投票率": 74.51000213623047,
      "李順涼": 500,
      "顏清標": 466
    },
    {
      "區別": "沙鹿區",
      "里別": "鹿峰里",
      "投票所": 193,
      "有效票數": 1147,
      "無效票數": 53,
      "投票數": 1200,
      "已領未投票數": 0,
      "發出票數": 1200,
      "用餘票數": 366,
      "選舉人數": 1566,
      "投票率": 76.62999725341797,
      "李順涼": 534,
      "顏清標": 613
    },
    {
      "區別": "沙鹿區",
      "里別": "鹿峰里",
      "投票所": 194,
      "有效票數": 1106,
      "無效票數": 43,
      "投票數": 1149,
      "已領未投票數": 0,
      "發出票數": 1149,
      "用餘票數": 379,
      "選舉人數": 1528,
      "投票率": 75.19999694824219,
      "李順涼": 464,
      "顏清標": 642
    },
    {
      "區別": "沙鹿區",
      "里別": "鹿寮里",
      "投票所": 195,
      "有效票數": 744,
      "無效票數": 33,
      "投票數": 777,
      "已領未投票數": 0,
      "發出票數": 777,
      "用餘票數": 299,
      "選舉人數": 1076,
      "投票率": 72.20999908447266,
      "李順涼": 360,
      "顏清標": 384
    },
    {
      "區別": "沙鹿區",
      "里別": "鹿寮里",
      "投票所": 196,
      "有效票數": 838,
      "無效票數": 48,
      "投票數": 886,
      "已領未投票數": 0,
      "發出票數": 886,
      "用餘票數": 310,
      "選舉人數": 1196,
      "投票率": 74.08000183105469,
      "李順涼": 376,
      "顏清標": 462
    },
    {
      "區別": "沙鹿區",
      "里別": "鹿寮里",
      "投票所": 197,
      "有效票數": 904,
      "無效票數": 42,
      "投票數": 946,
      "已領未投票數": 0,
      "發出票數": 946,
      "用餘票數": 251,
      "選舉人數": 1197,
      "投票率": 79.02999877929688,
      "李順涼": 433,
      "顏清標": 471
    },
    {
      "區別": "沙鹿區",
      "里別": "鹿寮里",
      "投票所": 198,
      "有效票數": 799,
      "無效票數": 30,
      "投票數": 829,
      "已領未投票數": 0,
      "發出票數": 829,
      "用餘票數": 241,
      "選舉人數": 1070,
      "投票率": 77.4800033569336,
      "李順涼": 407,
      "顏清標": 392
    },
    {
      "區別": "沙鹿區",
      "里別": "鹿寮里",
      "投票所": 199,
      "有效票數": 972,
      "無效票數": 54,
      "投票數": 1026,
      "已領未投票數": 0,
      "發出票數": 1026,
      "用餘票數": 276,
      "選舉人數": 1302,
      "投票率": 78.80000305175781,
      "李順涼": 393,
      "顏清標": 579
    },
    {
      "區別": "沙鹿區",
      "里別": "竹林里",
      "投票所": 200,
      "有效票數": 957,
      "無效票數": 45,
      "投票數": 1002,
      "已領未投票數": 0,
      "發出票數": 1002,
      "用餘票數": 326,
      "選舉人數": 1328,
      "投票率": 75.44999694824219,
      "李順涼": 332,
      "顏清標": 625
    },
    {
      "區別": "沙鹿區",
      "里別": "竹林里",
      "投票所": 201,
      "有效票數": 781,
      "無效票數": 39,
      "投票數": 820,
      "已領未投票數": 0,
      "發出票數": 820,
      "用餘票數": 284,
      "選舉人數": 1104,
      "投票率": 74.27999877929688,
      "李順涼": 283,
      "顏清標": 498
    },
    {
      "區別": "沙鹿區",
      "里別": "竹林里",
      "投票所": 202,
      "有效票數": 771,
      "無效票數": 32,
      "投票數": 803,
      "已領未投票數": 0,
      "發出票數": 803,
      "用餘票數": 259,
      "選舉人數": 1062,
      "投票率": 75.61000061035156,
      "李順涼": 214,
      "顏清標": 557
    },
    {
      "區別": "沙鹿區",
      "里別": "竹林里",
      "投票所": 203,
      "有效票數": 866,
      "無效票數": 47,
      "投票數": 913,
      "已領未投票數": 0,
      "發出票數": 913,
      "用餘票數": 328,
      "選舉人數": 1241,
      "投票率": 73.56999969482422,
      "李順涼": 308,
      "顏清標": 558
    },
    {
      "區別": "沙鹿區",
      "里別": "竹林里",
      "投票所": 204,
      "有效票數": 1256,
      "無效票數": 63,
      "投票數": 1319,
      "已領未投票數": 0,
      "發出票數": 1319,
      "用餘票數": 393,
      "選舉人數": 1712,
      "投票率": 77.04000091552734,
      "李順涼": 467,
      "顏清標": 789
    },
    {
      "區別": "沙鹿區",
      "里別": "犁分里",
      "投票所": 205,
      "有效票數": 709,
      "無效票數": 33,
      "投票數": 742,
      "已領未投票數": 0,
      "發出票數": 742,
      "用餘票數": 245,
      "選舉人數": 987,
      "投票率": 75.18000030517578,
      "李順涼": 255,
      "顏清標": 454
    },
    {
      "區別": "沙鹿區",
      "里別": "福興里",
      "投票所": 206,
      "有效票數": 1104,
      "無效票數": 37,
      "投票數": 1141,
      "已領未投票數": 0,
      "發出票數": 1141,
      "用餘票數": 387,
      "選舉人數": 1528,
      "投票率": 74.66999816894531,
      "李順涼": 353,
      "顏清標": 751
    },
    {
      "區別": "沙鹿區",
      "里別": "福興里",
      "投票所": 207,
      "有效票數": 1011,
      "無效票數": 35,
      "投票數": 1046,
      "已領未投票數": 0,
      "發出票數": 1046,
      "用餘票數": 369,
      "選舉人數": 1415,
      "投票率": 73.91999816894531,
      "李順涼": 258,
      "顏清標": 753
    },
    {
      "區別": "沙鹿區",
      "里別": "北勢里",
      "投票所": 208,
      "有效票數": 1056,
      "無效票數": 46,
      "投票數": 1102,
      "已領未投票數": 0,
      "發出票數": 1102,
      "用餘票數": 337,
      "選舉人數": 1439,
      "投票率": 76.58000183105469,
      "李順涼": 356,
      "顏清標": 700
    },
    {
      "區別": "沙鹿區",
      "里別": "北勢里",
      "投票所": 209,
      "有效票數": 988,
      "無效票數": 38,
      "投票數": 1026,
      "已領未投票數": 0,
      "發出票數": 1026,
      "用餘票數": 345,
      "選舉人數": 1371,
      "投票率": 74.83999633789062,
      "李順涼": 312,
      "顏清標": 676
    },
    {
      "區別": "沙鹿區",
      "里別": "北勢里",
      "投票所": 210,
      "有效票數": 816,
      "無效票數": 24,
      "投票數": 840,
      "已領未投票數": 0,
      "發出票數": 840,
      "用餘票數": 298,
      "選舉人數": 1138,
      "投票率": 73.80999755859375,
      "李順涼": 263,
      "顏清標": 553
    },
    {
      "區別": "沙鹿區",
      "里別": "晉江里",
      "投票所": 211,
      "有效票數": 1022,
      "無效票數": 39,
      "投票數": 1061,
      "已領未投票數": 0,
      "發出票數": 1061,
      "用餘票數": 306,
      "選舉人數": 1367,
      "投票率": 77.62000274658203,
      "李順涼": 382,
      "顏清標": 640
    },
    {
      "區別": "沙鹿區",
      "里別": "六路里",
      "投票所": 212,
      "有效票數": 877,
      "無效票數": 25,
      "投票數": 902,
      "已領未投票數": 0,
      "發出票數": 902,
      "用餘票數": 335,
      "選舉人數": 1237,
      "投票率": 72.91999816894531,
      "李順涼": 288,
      "顏清標": 589
    },
    {
      "區別": "沙鹿區",
      "里別": "六路里",
      "投票所": 213,
      "有效票數": 951,
      "無效票數": 34,
      "投票數": 985,
      "已領未投票數": 0,
      "發出票數": 985,
      "用餘票數": 307,
      "選舉人數": 1292,
      "投票率": 76.23999786376953,
      "李順涼": 296,
      "顏清標": 655
    },
    {
      "區別": "沙鹿區",
      "里別": "六路里",
      "投票所": 214,
      "有效票數": 798,
      "無效票數": 32,
      "投票數": 830,
      "已領未投票數": 0,
      "發出票數": 830,
      "用餘票數": 310,
      "選舉人數": 1140,
      "投票率": 72.80999755859375,
      "李順涼": 259,
      "顏清標": 539
    },
    {
      "區別": "沙鹿區",
      "里別": "南勢里",
      "投票所": 215,
      "有效票數": 824,
      "無效票數": 35,
      "投票數": 859,
      "已領未投票數": 0,
      "發出票數": 859,
      "用餘票數": 298,
      "選舉人數": 1157,
      "投票率": 74.23999786376953,
      "李順涼": 256,
      "顏清標": 568
    },
    {
      "區別": "沙鹿區",
      "里別": "南勢里",
      "投票所": 216,
      "有效票數": 1009,
      "無效票數": 28,
      "投票數": 1037,
      "已領未投票數": 0,
      "發出票數": 1037,
      "用餘票數": 348,
      "選舉人數": 1385,
      "投票率": 74.87000274658203,
      "李順涼": 292,
      "顏清標": 717
    },
    {
      "區別": "沙鹿區",
      "里別": "埔子里",
      "投票所": 217,
      "有效票數": 1302,
      "無效票數": 41,
      "投票數": 1343,
      "已領未投票數": 0,
      "發出票數": 1343,
      "用餘票數": 461,
      "選舉人數": 1804,
      "投票率": 74.44999694824219,
      "李順涼": 353,
      "顏清標": 949
    },
    {
      "區別": "沙鹿區",
      "里別": "埔子里",
      "投票所": 218,
      "有效票數": 1260,
      "無效票數": 34,
      "投票數": 1294,
      "已領未投票數": 0,
      "發出票數": 1294,
      "用餘票數": 411,
      "選舉人數": 1705,
      "投票率": 75.88999938964844,
      "李順涼": 308,
      "顏清標": 952
    },
    {
      "區別": "沙鹿區",
      "里別": "三鹿里",
      "投票所": 219,
      "有效票數": 1400,
      "無效票數": 68,
      "投票數": 1468,
      "已領未投票數": 0,
      "發出票數": 1468,
      "用餘票數": 476,
      "選舉人數": 1944,
      "投票率": 75.51000213623047,
      "李順涼": 390,
      "顏清標": 1010
    },
    {
      "區別": "沙鹿區",
      "里別": "三鹿里",
      "投票所": 220,
      "有效票數": 1403,
      "無效票數": 36,
      "投票數": 1439,
      "已領未投票數": 0,
      "發出票數": 1439,
      "用餘票數": 483,
      "選舉人數": 1922,
      "投票率": 74.87000274658203,
      "李順涼": 301,
      "顏清標": 1102
    },
    {
      "區別": "沙鹿區",
      "里別": "公明里",
      "投票所": 221,
      "有效票數": 1018,
      "無效票數": 31,
      "投票數": 1049,
      "已領未投票數": 0,
      "發出票數": 1049,
      "用餘票數": 345,
      "選舉人數": 1394,
      "投票率": 75.25,
      "李順涼": 352,
      "顏清標": 666
    },
    {
      "區別": "沙鹿區",
      "里別": "公明里",
      "投票所": 222,
      "有效票數": 543,
      "無效票數": 18,
      "投票數": 561,
      "已領未投票數": 0,
      "發出票數": 561,
      "用餘票數": 174,
      "選舉人數": 735,
      "投票率": 76.33000183105469,
      "李順涼": 67,
      "顏清標": 476
    },
    {
      "區別": "沙鹿區",
      "里別": "公明里",
      "投票所": 223,
      "有效票數": 1082,
      "無效票數": 36,
      "投票數": 1118,
      "已領未投票數": 0,
      "發出票數": 1118,
      "用餘票數": 325,
      "選舉人數": 1443,
      "投票率": 77.4800033569336,
      "李順涼": 397,
      "顏清標": 685
    },
    {
      "區別": "沙鹿區",
      "里別": "清泉里",
      "投票所": 224,
      "有效票數": 885,
      "無效票數": 22,
      "投票數": 907,
      "已領未投票數": 0,
      "發出票數": 907,
      "用餘票數": 231,
      "選舉人數": 1138,
      "投票率": 79.69999694824219,
      "李順涼": 305,
      "顏清標": 580
    },
    {
      "區別": "沙鹿區",
      "里別": "清泉里",
      "投票所": 225,
      "有效票數": 645,
      "無效票數": 15,
      "投票數": 660,
      "已領未投票數": 0,
      "發出票數": 660,
      "用餘票數": 180,
      "選舉人數": 840,
      "投票率": 78.56999969482422,
      "李順涼": 150,
      "顏清標": 495
    },
    {
      "區別": "沙鹿區",
      "里別": "西勢里",
      "投票所": 226,
      "有效票數": 770,
      "無效票數": 40,
      "投票數": 810,
      "已領未投票數": 0,
      "發出票數": 810,
      "用餘票數": 244,
      "選舉人數": 1054,
      "投票率": 76.8499984741211,
      "李順涼": 285,
      "顏清標": 485
    },
    {
      "區別": "沙鹿區",
      "里別": "西勢里",
      "投票所": 227,
      "有效票數": 706,
      "無效票數": 36,
      "投票數": 742,
      "已領未投票數": 0,
      "發出票數": 742,
      "用餘票數": 231,
      "選舉人數": 973,
      "投票率": 76.26000213623047,
      "李順涼": 205,
      "顏清標": 501
    },
    {
      "區別": "龍井區",
      "里別": "竹坑里",
      "投票所": 228,
      "有效票數": 1007,
      "無效票數": 39,
      "投票數": 1046,
      "已領未投票數": 0,
      "發出票數": 1046,
      "用餘票數": 467,
      "選舉人數": 1513,
      "投票率": 69.12999725341797,
      "李順涼": 332,
      "顏清標": 675
    },
    {
      "區別": "龍井區",
      "里別": "竹坑里",
      "投票所": 229,
      "有效票數": 788,
      "無效票數": 18,
      "投票數": 806,
      "已領未投票數": 0,
      "發出票數": 806,
      "用餘票數": 286,
      "選舉人數": 1092,
      "投票率": 73.80999755859375,
      "李順涼": 233,
      "顏清標": 555
    },
    {
      "區別": "龍井區",
      "里別": "龍東里",
      "投票所": 230,
      "有效票數": 968,
      "無效票數": 21,
      "投票數": 989,
      "已領未投票數": 0,
      "發出票數": 989,
      "用餘票數": 338,
      "選舉人數": 1327,
      "投票率": 74.52999877929688,
      "李順涼": 349,
      "顏清標": 619
    },
    {
      "區別": "龍井區",
      "里別": "龍東里",
      "投票所": 231,
      "有效票數": 898,
      "無效票數": 25,
      "投票數": 923,
      "已領未投票數": 0,
      "發出票數": 923,
      "用餘票數": 310,
      "選舉人數": 1233,
      "投票率": 74.86000061035156,
      "李順涼": 297,
      "顏清標": 601
    },
    {
      "區別": "龍井區",
      "里別": "龍西里",
      "投票所": 232,
      "有效票數": 1214,
      "無效票數": 32,
      "投票數": 1246,
      "已領未投票數": 0,
      "發出票數": 1246,
      "用餘票數": 438,
      "選舉人數": 1684,
      "投票率": 73.98999786376953,
      "李順涼": 408,
      "顏清標": 806
    },
    {
      "區別": "龍井區",
      "里別": "田中里",
      "投票所": 233,
      "有效票數": 1167,
      "無效票數": 33,
      "投票數": 1200,
      "已領未投票數": 0,
      "發出票數": 1200,
      "用餘票數": 405,
      "選舉人數": 1605,
      "投票率": 74.7699966430664,
      "李順涼": 430,
      "顏清標": 737
    },
    {
      "區別": "龍井區",
      "里別": "田中里",
      "投票所": 234,
      "有效票數": 1001,
      "無效票數": 25,
      "投票數": 1026,
      "已領未投票數": 0,
      "發出票數": 1026,
      "用餘票數": 344,
      "選舉人數": 1370,
      "投票率": 74.88999938964844,
      "李順涼": 378,
      "顏清標": 623
    },
    {
      "區別": "龍井區",
      "里別": "福田里",
      "投票所": 235,
      "有效票數": 679,
      "無效票數": 21,
      "投票數": 700,
      "已領未投票數": 0,
      "發出票數": 700,
      "用餘票數": 275,
      "選舉人數": 975,
      "投票率": 71.79000091552734,
      "李順涼": 215,
      "顏清標": 464
    },
    {
      "區別": "龍井區",
      "里別": "麗水里",
      "投票所": 236,
      "有效票數": 852,
      "無效票數": 21,
      "投票數": 873,
      "已領未投票數": 0,
      "發出票數": 873,
      "用餘票數": 287,
      "選舉人數": 1160,
      "投票率": 75.26000213623047,
      "李順涼": 223,
      "顏清標": 629
    },
    {
      "區別": "龍井區",
      "里別": "麗水里",
      "投票所": 237,
      "有效票數": 625,
      "無效票數": 11,
      "投票數": 636,
      "已領未投票數": 0,
      "發出票數": 636,
      "用餘票數": 252,
      "選舉人數": 888,
      "投票率": 71.62000274658203,
      "李順涼": 198,
      "顏清標": 427
    },
    {
      "區別": "龍井區",
      "里別": "龍津里",
      "投票所": 238,
      "有效票數": 1019,
      "無效票數": 52,
      "投票數": 1071,
      "已領未投票數": 0,
      "發出票數": 1071,
      "用餘票數": 413,
      "選舉人數": 1484,
      "投票率": 72.16999816894531,
      "李順涼": 358,
      "顏清標": 661
    },
    {
      "區別": "龍井區",
      "里別": "龍津里",
      "投票所": 239,
      "有效票數": 806,
      "無效票數": 9,
      "投票數": 815,
      "已領未投票數": 0,
      "發出票數": 815,
      "用餘票數": 291,
      "選舉人數": 1106,
      "投票率": 73.69000244140625,
      "李順涼": 272,
      "顏清標": 534
    },
    {
      "區別": "龍井區",
      "里別": "龍津里",
      "投票所": 240,
      "有效票數": 843,
      "無效票數": 28,
      "投票數": 871,
      "已領未投票數": 0,
      "發出票數": 871,
      "用餘票數": 279,
      "選舉人數": 1150,
      "投票率": 75.73999786376953,
      "李順涼": 319,
      "顏清標": 524
    },
    {
      "區別": "龍井區",
      "里別": "龍津里",
      "投票所": 241,
      "有效票數": 637,
      "無效票數": 25,
      "投票數": 662,
      "已領未投票數": 0,
      "發出票數": 662,
      "用餘票數": 231,
      "選舉人數": 893,
      "投票率": 74.12999725341797,
      "李順涼": 320,
      "顏清標": 317
    },
    {
      "區別": "龍井區",
      "里別": "三德里",
      "投票所": 242,
      "有效票數": 1110,
      "無效票數": 36,
      "投票數": 1146,
      "已領未投票數": 0,
      "發出票數": 1146,
      "用餘票數": 447,
      "選舉人數": 1593,
      "投票率": 71.94000244140625,
      "李順涼": 435,
      "顏清標": 675
    },
    {
      "區別": "龍井區",
      "里別": "三德里",
      "投票所": 243,
      "有效票數": 852,
      "無效票數": 27,
      "投票數": 879,
      "已領未投票數": 0,
      "發出票數": 879,
      "用餘票數": 298,
      "選舉人數": 1177,
      "投票率": 74.68000030517578,
      "李順涼": 342,
      "顏清標": 510
    },
    {
      "區別": "龍井區",
      "里別": "忠和里",
      "投票所": 244,
      "有效票數": 964,
      "無效票數": 37,
      "投票數": 1001,
      "已領未投票數": 0,
      "發出票數": 1001,
      "用餘票數": 313,
      "選舉人數": 1314,
      "投票率": 76.18000030517578,
      "李順涼": 319,
      "顏清標": 645
    },
    {
      "區別": "龍井區",
      "里別": "忠和里",
      "投票所": 245,
      "有效票數": 1086,
      "無效票數": 39,
      "投票數": 1125,
      "已領未投票數": 0,
      "發出票數": 1125,
      "用餘票數": 433,
      "選舉人數": 1558,
      "投票率": 72.20999908447266,
      "李順涼": 406,
      "顏清標": 680
    },
    {
      "區別": "龍井區",
      "里別": "忠和里",
      "投票所": 246,
      "有效票數": 1065,
      "無效票數": 23,
      "投票數": 1088,
      "已領未投票數": 0,
      "發出票數": 1088,
      "用餘票數": 349,
      "選舉人數": 1437,
      "投票率": 75.70999908447266,
      "李順涼": 426,
      "顏清標": 639
    },
    {
      "區別": "龍井區",
      "里別": "山腳里",
      "投票所": 247,
      "有效票數": 1021,
      "無效票數": 28,
      "投票數": 1049,
      "已領未投票數": 0,
      "發出票數": 1049,
      "用餘票數": 413,
      "選舉人數": 1462,
      "投票率": 71.75,
      "李順涼": 318,
      "顏清標": 703
    },
    {
      "區別": "龍井區",
      "里別": "山腳里",
      "投票所": 248,
      "有效票數": 1181,
      "無效票數": 23,
      "投票數": 1204,
      "已領未投票數": 0,
      "發出票數": 1204,
      "用餘票數": 452,
      "選舉人數": 1656,
      "投票率": 72.70999908447266,
      "李順涼": 447,
      "顏清標": 734
    },
    {
      "區別": "龍井區",
      "里別": "山腳里",
      "投票所": 249,
      "有效票數": 1105,
      "無效票數": 22,
      "投票數": 1127,
      "已領未投票數": 0,
      "發出票數": 1127,
      "用餘票數": 419,
      "選舉人數": 1546,
      "投票率": 72.9000015258789,
      "李順涼": 399,
      "顏清標": 706
    },
    {
      "區別": "龍井區",
      "里別": "龍泉里",
      "投票所": 250,
      "有效票數": 936,
      "無效票數": 63,
      "投票數": 999,
      "已領未投票數": 0,
      "發出票數": 999,
      "用餘票數": 322,
      "選舉人數": 1321,
      "投票率": 75.62000274658203,
      "李順涼": 344,
      "顏清標": 592
    },
    {
      "區別": "龍井區",
      "里別": "龍泉里",
      "投票所": 251,
      "有效票數": 972,
      "無效票數": 29,
      "投票數": 1001,
      "已領未投票數": 0,
      "發出票數": 1001,
      "用餘票數": 510,
      "選舉人數": 1511,
      "投票率": 66.25,
      "李順涼": 395,
      "顏清標": 577
    },
    {
      "區別": "龍井區",
      "里別": "龍泉里",
      "投票所": 252,
      "有效票數": 963,
      "無效票數": 32,
      "投票數": 995,
      "已領未投票數": 0,
      "發出票數": 995,
      "用餘票數": 309,
      "選舉人數": 1304,
      "投票率": 76.30000305175781,
      "李順涼": 347,
      "顏清標": 616
    },
    {
      "區別": "龍井區",
      "里別": "龍泉里",
      "投票所": 253,
      "有效票數": 1170,
      "無效票數": 42,
      "投票數": 1212,
      "已領未投票數": 0,
      "發出票數": 1212,
      "用餘票數": 453,
      "選舉人數": 1665,
      "投票率": 72.79000091552734,
      "李順涼": 372,
      "顏清標": 798
    },
    {
      "區別": "龍井區",
      "里別": "龍崗里",
      "投票所": 254,
      "有效票數": 1001,
      "無效票數": 28,
      "投票數": 1029,
      "已領未投票數": 0,
      "發出票數": 1029,
      "用餘票數": 383,
      "選舉人數": 1412,
      "投票率": 72.87999725341797,
      "李順涼": 388,
      "顏清標": 613
    },
    {
      "區別": "龍井區",
      "里別": "龍崗里",
      "投票所": 255,
      "有效票數": 636,
      "無效票數": 15,
      "投票數": 651,
      "已領未投票數": 0,
      "發出票數": 651,
      "用餘票數": 187,
      "選舉人數": 838,
      "投票率": 77.68000030517578,
      "李順涼": 219,
      "顏清標": 417
    },
    {
      "區別": "龍井區",
      "里別": "新庄里",
      "投票所": 256,
      "有效票數": 1216,
      "無效票數": 37,
      "投票數": 1253,
      "已領未投票數": 0,
      "發出票數": 1253,
      "用餘票數": 482,
      "選舉人數": 1735,
      "投票率": 72.22000122070312,
      "李順涼": 459,
      "顏清標": 757
    },
    {
      "區別": "龍井區",
      "里別": "新庄里",
      "投票所": 257,
      "有效票數": 1179,
      "無效票數": 33,
      "投票數": 1212,
      "已領未投票數": 0,
      "發出票數": 1212,
      "用餘票數": 434,
      "選舉人數": 1646,
      "投票率": 73.62999725341797,
      "李順涼": 469,
      "顏清標": 710
    },
    {
      "區別": "龍井區",
      "里別": "新庄里",
      "投票所": 258,
      "有效票數": 1496,
      "無效票數": 55,
      "投票數": 1551,
      "已領未投票數": 0,
      "發出票數": 1551,
      "用餘票數": 534,
      "選舉人數": 2085,
      "投票率": 74.38999938964844,
      "李順涼": 626,
      "顏清標": 870
    },
    {
      "區別": "龍井區",
      "里別": "南寮里",
      "投票所": 259,
      "有效票數": 1134,
      "無效票數": 31,
      "投票數": 1165,
      "已領未投票數": 0,
      "發出票數": 1165,
      "用餘票數": 293,
      "選舉人數": 1458,
      "投票率": 79.9000015258789,
      "李順涼": 385,
      "顏清標": 749
    },
    {
      "區別": "龍井區",
      "里別": "東海里",
      "投票所": 260,
      "有效票數": 1201,
      "無效票數": 63,
      "投票數": 1264,
      "已領未投票數": 0,
      "發出票數": 1264,
      "用餘票數": 436,
      "選舉人數": 1700,
      "投票率": 74.3499984741211,
      "李順涼": 415,
      "顏清標": 786
    },
    {
      "區別": "龍井區",
      "里別": "東海里",
      "投票所": 261,
      "有效票數": 1262,
      "無效票數": 85,
      "投票數": 1347,
      "已領未投票數": 0,
      "發出票數": 1347,
      "用餘票數": 436,
      "選舉人數": 1783,
      "投票率": 75.55000305175781,
      "李順涼": 490,
      "顏清標": 772
    },
    {
      "區別": "龍井區",
      "里別": "東海里",
      "投票所": 262,
      "有效票數": 1127,
      "無效票數": 70,
      "投票數": 1197,
      "已領未投票數": 0,
      "發出票數": 1197,
      "用餘票數": 395,
      "選舉人數": 1592,
      "投票率": 75.19000244140625,
      "李順涼": 382,
      "顏清標": 745
    },
    {
      "區別": "龍井區",
      "里別": "東海里",
      "投票所": 263,
      "有效票數": 1155,
      "無效票數": 48,
      "投票數": 1203,
      "已領未投票數": 0,
      "發出票數": 1203,
      "用餘票數": 404,
      "選舉人數": 1607,
      "投票率": 74.86000061035156,
      "李順涼": 469,
      "顏清標": 686
    },
    {
      "區別": "龍井區",
      "里別": "新東里",
      "投票所": 264,
      "有效票數": 1335,
      "無效票數": 41,
      "投票數": 1376,
      "已領未投票數": 0,
      "發出票數": 1376,
      "用餘票數": 452,
      "選舉人數": 1828,
      "投票率": 75.2699966430664,
      "李順涼": 601,
      "顏清標": 734
    },
    {
      "區別": "龍井區",
      "里別": "新東里",
      "投票所": 265,
      "有效票數": 1595,
      "無效票數": 56,
      "投票數": 1651,
      "已領未投票數": 0,
      "發出票數": 1651,
      "用餘票數": 572,
      "選舉人數": 2223,
      "投票率": 74.2699966430664,
      "李順涼": 589,
      "顏清標": 1006
    },
    {
      "區別": "大肚區",
      "里別": "王田里",
      "投票所": 266,
      "有效票數": 946,
      "無效票數": 30,
      "投票數": 976,
      "已領未投票數": 1,
      "發出票數": 977,
      "用餘票數": 316,
      "選舉人數": 1293,
      "投票率": 75.4800033569336,
      "李順涼": 387,
      "顏清標": 559
    },
    {
      "區別": "大肚區",
      "里別": "王田里",
      "投票所": 267,
      "有效票數": 831,
      "無效票數": 45,
      "投票數": 876,
      "已領未投票數": 0,
      "發出票數": 876,
      "用餘票數": 357,
      "選舉人數": 1233,
      "投票率": 71.05000305175781,
      "李順涼": 325,
      "顏清標": 506
    },
    {
      "區別": "大肚區",
      "里別": "王田里",
      "投票所": 268,
      "有效票數": 1077,
      "無效票數": 32,
      "投票數": 1109,
      "已領未投票數": 0,
      "發出票數": 1109,
      "用餘票數": 324,
      "選舉人數": 1433,
      "投票率": 77.38999938964844,
      "李順涼": 482,
      "顏清標": 595
    },
    {
      "區別": "大肚區",
      "里別": "中和里",
      "投票所": 269,
      "有效票數": 605,
      "無效票數": 29,
      "投票數": 634,
      "已領未投票數": 0,
      "發出票數": 634,
      "用餘票數": 181,
      "選舉人數": 815,
      "投票率": 77.79000091552734,
      "李順涼": 281,
      "顏清標": 324
    },
    {
      "區別": "大肚區",
      "里別": "福山里",
      "投票所": 270,
      "有效票數": 838,
      "無效票數": 42,
      "投票數": 880,
      "已領未投票數": 0,
      "發出票數": 880,
      "用餘票數": 250,
      "選舉人數": 1130,
      "投票率": 77.87999725341797,
      "李順涼": 363,
      "顏清標": 475
    },
    {
      "區別": "大肚區",
      "里別": "福山里",
      "投票所": 271,
      "有效票數": 868,
      "無效票數": 61,
      "投票數": 929,
      "已領未投票數": 0,
      "發出票數": 929,
      "用餘票數": 272,
      "選舉人數": 1201,
      "投票率": 77.3499984741211,
      "李順涼": 378,
      "顏清標": 490
    },
    {
      "區別": "大肚區",
      "里別": "福山里",
      "投票所": 272,
      "有效票數": 774,
      "無效票數": 29,
      "投票數": 803,
      "已領未投票數": 0,
      "發出票數": 803,
      "用餘票數": 244,
      "選舉人數": 1047,
      "投票率": 76.69999694824219,
      "李順涼": 343,
      "顏清標": 431
    },
    {
      "區別": "大肚區",
      "里別": "營埔里",
      "投票所": 273,
      "有效票數": 997,
      "無效票數": 39,
      "投票數": 1036,
      "已領未投票數": 0,
      "發出票數": 1036,
      "用餘票數": 332,
      "選舉人數": 1368,
      "投票率": 75.7300033569336,
      "李順涼": 379,
      "顏清標": 618
    },
    {
      "區別": "大肚區",
      "里別": "社腳里",
      "投票所": 274,
      "有效票數": 832,
      "無效票數": 34,
      "投票數": 866,
      "已領未投票數": 0,
      "發出票數": 866,
      "用餘票數": 247,
      "選舉人數": 1113,
      "投票率": 77.80999755859375,
      "李順涼": 305,
      "顏清標": 527
    },
    {
      "區別": "大肚區",
      "里別": "社腳里",
      "投票所": 275,
      "有效票數": 846,
      "無效票數": 23,
      "投票數": 869,
      "已領未投票數": 0,
      "發出票數": 869,
      "用餘票數": 260,
      "選舉人數": 1129,
      "投票率": 76.97000122070312,
      "李順涼": 334,
      "顏清標": 512
    },
    {
      "區別": "大肚區",
      "里別": "新興里",
      "投票所": 276,
      "有效票數": 918,
      "無效票數": 29,
      "投票數": 947,
      "已領未投票數": 0,
      "發出票數": 947,
      "用餘票數": 289,
      "選舉人數": 1236,
      "投票率": 76.62000274658203,
      "李順涼": 319,
      "顏清標": 599
    },
    {
      "區別": "大肚區",
      "里別": "新興里",
      "投票所": 277,
      "有效票數": 771,
      "無效票數": 21,
      "投票數": 792,
      "已領未投票數": 0,
      "發出票數": 792,
      "用餘票數": 291,
      "選舉人數": 1083,
      "投票率": 73.12999725341797,
      "李順涼": 279,
      "顏清標": 492
    },
    {
      "區別": "大肚區",
      "里別": "大東里",
      "投票所": 278,
      "有效票數": 1093,
      "無效票數": 43,
      "投票數": 1136,
      "已領未投票數": 0,
      "發出票數": 1136,
      "用餘票數": 382,
      "選舉人數": 1518,
      "投票率": 74.83999633789062,
      "李順涼": 396,
      "顏清標": 697
    },
    {
      "區別": "大肚區",
      "里別": "大東里",
      "投票所": 279,
      "有效票數": 839,
      "無效票數": 50,
      "投票數": 889,
      "已領未投票數": 0,
      "發出票數": 889,
      "用餘票數": 283,
      "選舉人數": 1172,
      "投票率": 75.8499984741211,
      "李順涼": 347,
      "顏清標": 492
    },
    {
      "區別": "大肚區",
      "里別": "大肚里",
      "投票所": 280,
      "有效票數": 585,
      "無效票數": 13,
      "投票數": 598,
      "已領未投票數": 0,
      "發出票數": 598,
      "用餘票數": 165,
      "選舉人數": 763,
      "投票率": 78.37000274658203,
      "李順涼": 242,
      "顏清標": 343
    },
    {
      "區別": "大肚區",
      "里別": "大肚里",
      "投票所": 281,
      "有效票數": 795,
      "無效票數": 36,
      "投票數": 831,
      "已領未投票數": 0,
      "發出票數": 831,
      "用餘票數": 203,
      "選舉人數": 1034,
      "投票率": 80.37000274658203,
      "李順涼": 304,
      "顏清標": 491
    },
    {
      "區別": "大肚區",
      "里別": "永和里",
      "投票所": 282,
      "有效票數": 644,
      "無效票數": 26,
      "投票數": 670,
      "已領未投票數": 0,
      "發出票數": 670,
      "用餘票數": 159,
      "選舉人數": 829,
      "投票率": 80.81999969482422,
      "李順涼": 261,
      "顏清標": 383
    },
    {
      "區別": "大肚區",
      "里別": "磺溪里",
      "投票所": 283,
      "有效票數": 1089,
      "無效票數": 27,
      "投票數": 1116,
      "已領未投票數": 0,
      "發出票數": 1116,
      "用餘票數": 327,
      "選舉人數": 1443,
      "投票率": 77.33999633789062,
      "李順涼": 410,
      "顏清標": 679
    },
    {
      "區別": "大肚區",
      "里別": "永順里",
      "投票所": 284,
      "有效票數": 1187,
      "無效票數": 26,
      "投票數": 1213,
      "已領未投票數": 0,
      "發出票數": 1213,
      "用餘票數": 347,
      "選舉人數": 1560,
      "投票率": 77.76000213623047,
      "李順涼": 488,
      "顏清標": 699
    },
    {
      "區別": "大肚區",
      "里別": "成功里",
      "投票所": 285,
      "有效票數": 676,
      "無效票數": 15,
      "投票數": 691,
      "已領未投票數": 0,
      "發出票數": 691,
      "用餘票數": 221,
      "選舉人數": 912,
      "投票率": 75.7699966430664,
      "李順涼": 231,
      "顏清標": 445
    },
    {
      "區別": "大肚區",
      "里別": "山陽里",
      "投票所": 286,
      "有效票數": 964,
      "無效票數": 23,
      "投票數": 987,
      "已領未投票數": 0,
      "發出票數": 987,
      "用餘票數": 298,
      "選舉人數": 1285,
      "投票率": 76.80999755859375,
      "李順涼": 376,
      "顏清標": 588
    },
    {
      "區別": "大肚區",
      "里別": "頂街里",
      "投票所": 287,
      "有效票數": 1243,
      "無效票數": 47,
      "投票數": 1290,
      "已領未投票數": 0,
      "發出票數": 1290,
      "用餘票數": 516,
      "選舉人數": 1806,
      "投票率": 71.43000030517578,
      "李順涼": 575,
      "顏清標": 668
    },
    {
      "區別": "大肚區",
      "里別": "頂街里",
      "投票所": 288,
      "有效票數": 1174,
      "無效票數": 32,
      "投票數": 1206,
      "已領未投票數": 0,
      "發出票數": 1206,
      "用餘票數": 401,
      "選舉人數": 1607,
      "投票率": 75.05000305175781,
      "李順涼": 486,
      "顏清標": 688
    },
    {
      "區別": "大肚區",
      "里別": "頂街里",
      "投票所": 289,
      "有效票數": 966,
      "無效票數": 46,
      "投票數": 1012,
      "已領未投票數": 1,
      "發出票數": 1013,
      "用餘票數": 276,
      "選舉人數": 1289,
      "投票率": 78.51000213623047,
      "李順涼": 369,
      "顏清標": 597
    },
    {
      "區別": "大肚區",
      "里別": "頂街里",
      "投票所": 290,
      "有效票數": 1001,
      "無效票數": 30,
      "投票數": 1031,
      "已領未投票數": 1,
      "發出票數": 1032,
      "用餘票數": 285,
      "選舉人數": 1317,
      "投票率": 78.27999877929688,
      "李順涼": 379,
      "顏清標": 622
    },
    {
      "區別": "大肚區",
      "里別": "瑞井里",
      "投票所": 291,
      "有效票數": 1140,
      "無效票數": 64,
      "投票數": 1204,
      "已領未投票數": 0,
      "發出票數": 1204,
      "用餘票數": 311,
      "選舉人數": 1515,
      "投票率": 79.47000122070312,
      "李順涼": 458,
      "顏清標": 682
    },
    {
      "區別": "大肚區",
      "里別": "瑞井里",
      "投票所": 292,
      "有效票數": 1014,
      "無效票數": 29,
      "投票數": 1043,
      "已領未投票數": 0,
      "發出票數": 1043,
      "用餘票數": 361,
      "選舉人數": 1404,
      "投票率": 74.29000091552734,
      "李順涼": 438,
      "顏清標": 576
    },
    {
      "區別": "大肚區",
      "里別": "瑞井里",
      "投票所": 293,
      "有效票數": 869,
      "無效票數": 41,
      "投票數": 910,
      "已領未投票數": 0,
      "發出票數": 910,
      "用餘票數": 333,
      "選舉人數": 1243,
      "投票率": 73.20999908447266,
      "李順涼": 355,
      "顏清標": 514
    },
    {
      "區別": "大肚區",
      "里別": "蔗里",
      "投票所": 294,
      "有效票數": 1020,
      "無效票數": 26,
      "投票數": 1046,
      "已領未投票數": 0,
      "發出票數": 1046,
      "用餘票數": 325,
      "選舉人數": 1371,
      "投票率": 76.29000091552734,
      "李順涼": 491,
      "顏清標": 529
    },
    {
      "區別": "大肚區",
      "里別": "蔗里",
      "投票所": 295,
      "有效票數": 987,
      "無效票數": 18,
      "投票數": 1005,
      "已領未投票數": 0,
      "發出票數": 1005,
      "用餘票數": 345,
      "選舉人數": 1350,
      "投票率": 74.44000244140625,
      "李順涼": 407,
      "顏清標": 580
    },
    {
      "區別": "大肚區",
      "里別": "蔗里",
      "投票所": 296,
      "有效票數": 819,
      "無效票數": 32,
      "投票數": 851,
      "已領未投票數": 0,
      "發出票數": 851,
      "用餘票數": 306,
      "選舉人數": 1157,
      "投票率": 73.55000305175781,
      "李順涼": 355,
      "顏清標": 464
    },
    {
      "區別": "大肚區",
      "里別": "自強里",
      "投票所": 297,
      "有效票數": 1271,
      "無效票數": 47,
      "投票數": 1318,
      "已領未投票數": 0,
      "發出票數": 1318,
      "用餘票數": 430,
      "選舉人數": 1748,
      "投票率": 75.4000015258789,
      "李順涼": 522,
      "顏清標": 749
    },
    {
      "區別": "大肚區",
      "里別": "自強里",
      "投票所": 298,
      "有效票數": 1064,
      "無效票數": 45,
      "投票數": 1109,
      "已領未投票數": 0,
      "發出票數": 1109,
      "用餘票數": 294,
      "選舉人數": 1403,
      "投票率": 79.04000091552734,
      "李順涼": 246,
      "顏清標": 818
    },
    {
      "區別": "烏日區",
      "里別": "烏日里",
      "投票所": 299,
      "有效票數": 1380,
      "無效票數": 37,
      "投票數": 1417,
      "已領未投票數": 0,
      "發出票數": 1417,
      "用餘票數": 393,
      "選舉人數": 1810,
      "投票率": 78.29000091552734,
      "李順涼": 633,
      "顏清標": 747
    },
    {
      "區別": "烏日區",
      "里別": "烏日里",
      "投票所": 300,
      "有效票數": 1314,
      "無效票數": 43,
      "投票數": 1357,
      "已領未投票數": 0,
      "發出票數": 1357,
      "用餘票數": 366,
      "選舉人數": 1723,
      "投票率": 78.76000213623047,
      "李順涼": 666,
      "顏清標": 648
    },
    {
      "區別": "烏日區",
      "里別": "烏日里",
      "投票所": 301,
      "有效票數": 1158,
      "無效票數": 35,
      "投票數": 1193,
      "已領未投票數": 0,
      "發出票數": 1193,
      "用餘票數": 390,
      "選舉人數": 1583,
      "投票率": 75.36000061035156,
      "李順涼": 588,
      "顏清標": 570
    },
    {
      "區別": "烏日區",
      "里別": "烏日里",
      "投票所": 302,
      "有效票數": 1456,
      "無效票數": 53,
      "投票數": 1509,
      "已領未投票數": 0,
      "發出票數": 1509,
      "用餘票數": 427,
      "選舉人數": 1936,
      "投票率": 77.94000244140625,
      "李順涼": 612,
      "顏清標": 844
    },
    {
      "區別": "烏日區",
      "里別": "湖日里",
      "投票所": 303,
      "有效票數": 860,
      "無效票數": 23,
      "投票數": 883,
      "已領未投票數": 0,
      "發出票數": 883,
      "用餘票數": 274,
      "選舉人數": 1157,
      "投票率": 76.31999969482422,
      "李順涼": 418,
      "顏清標": 442
    },
    {
      "區別": "烏日區",
      "里別": "湖日里",
      "投票所": 304,
      "有效票數": 759,
      "無效票數": 22,
      "投票數": 781,
      "已領未投票數": 0,
      "發出票數": 781,
      "用餘票數": 314,
      "選舉人數": 1095,
      "投票率": 71.31999969482422,
      "李順涼": 343,
      "顏清標": 416
    },
    {
      "區別": "烏日區",
      "里別": "三和里",
      "投票所": 305,
      "有效票數": 1358,
      "無效票數": 32,
      "投票數": 1390,
      "已領未投票數": 0,
      "發出票數": 1390,
      "用餘票數": 508,
      "選舉人數": 1898,
      "投票率": 73.2300033569336,
      "李順涼": 617,
      "顏清標": 741
    },
    {
      "區別": "烏日區",
      "里別": "三和里",
      "投票所": 306,
      "有效票數": 1205,
      "無效票數": 25,
      "投票數": 1230,
      "已領未投票數": 0,
      "發出票數": 1230,
      "用餘票數": 436,
      "選舉人數": 1666,
      "投票率": 73.83000183105469,
      "李順涼": 332,
      "顏清標": 873
    },
    {
      "區別": "烏日區",
      "里別": "榮泉里",
      "投票所": 307,
      "有效票數": 1119,
      "無效票數": 48,
      "投票數": 1167,
      "已領未投票數": 0,
      "發出票數": 1167,
      "用餘票數": 364,
      "選舉人數": 1531,
      "投票率": 76.22000122070312,
      "李順涼": 431,
      "顏清標": 688
    },
    {
      "區別": "烏日區",
      "里別": "榮泉里",
      "投票所": 308,
      "有效票數": 869,
      "無效票數": 40,
      "投票數": 909,
      "已領未投票數": 0,
      "發出票數": 909,
      "用餘票數": 291,
      "選舉人數": 1200,
      "投票率": 75.75,
      "李順涼": 353,
      "顏清標": 516
    },
    {
      "區別": "烏日區",
      "里別": "學田里",
      "投票所": 309,
      "有效票數": 828,
      "無效票數": 30,
      "投票數": 858,
      "已領未投票數": 0,
      "發出票數": 858,
      "用餘票數": 251,
      "選舉人數": 1109,
      "投票率": 77.37000274658203,
      "李順涼": 323,
      "顏清標": 505
    },
    {
      "區別": "烏日區",
      "里別": "學田里",
      "投票所": 310,
      "有效票數": 696,
      "無效票數": 25,
      "投票數": 721,
      "已領未投票數": 0,
      "發出票數": 721,
      "用餘票數": 253,
      "選舉人數": 974,
      "投票率": 74.0199966430664,
      "李順涼": 287,
      "顏清標": 409
    },
    {
      "區別": "烏日區",
      "里別": "九德里",
      "投票所": 311,
      "有效票數": 1184,
      "無效票數": 28,
      "投票數": 1212,
      "已領未投票數": 0,
      "發出票數": 1212,
      "用餘票數": 337,
      "選舉人數": 1549,
      "投票率": 78.23999786376953,
      "李順涼": 564,
      "顏清標": 620
    },
    {
      "區別": "烏日區",
      "里別": "九德里",
      "投票所": 312,
      "有效票數": 1229,
      "無效票數": 32,
      "投票數": 1261,
      "已領未投票數": 0,
      "發出票數": 1261,
      "用餘票數": 379,
      "選舉人數": 1640,
      "投票率": 76.88999938964844,
      "李順涼": 510,
      "顏清標": 719
    },
    {
      "區別": "烏日區",
      "里別": "九德里",
      "投票所": 313,
      "有效票數": 1112,
      "無效票數": 30,
      "投票數": 1142,
      "已領未投票數": 0,
      "發出票數": 1142,
      "用餘票數": 353,
      "選舉人數": 1495,
      "投票率": 76.38999938964844,
      "李順涼": 469,
      "顏清標": 643
    },
    {
      "區別": "烏日區",
      "里別": "九德里",
      "投票所": 314,
      "有效票數": 1232,
      "無效票數": 34,
      "投票數": 1266,
      "已領未投票數": 0,
      "發出票數": 1266,
      "用餘票數": 440,
      "選舉人數": 1706,
      "投票率": 74.20999908447266,
      "李順涼": 569,
      "顏清標": 663
    },
    {
      "區別": "烏日區",
      "里別": "九德里",
      "投票所": 315,
      "有效票數": 1217,
      "無效票數": 30,
      "投票數": 1247,
      "已領未投票數": 0,
      "發出票數": 1247,
      "用餘票數": 330,
      "選舉人數": 1577,
      "投票率": 79.06999969482422,
      "李順涼": 633,
      "顏清標": 584
    },
    {
      "區別": "烏日區",
      "里別": "九德里",
      "投票所": 316,
      "有效票數": 1151,
      "無效票數": 25,
      "投票數": 1176,
      "已領未投票數": 0,
      "發出票數": 1176,
      "用餘票數": 336,
      "選舉人數": 1512,
      "投票率": 77.77999877929688,
      "李順涼": 590,
      "顏清標": 561
    },
    {
      "區別": "烏日區",
      "里別": "九德里",
      "投票所": 317,
      "有效票數": 1179,
      "無效票數": 32,
      "投票數": 1211,
      "已領未投票數": 0,
      "發出票數": 1211,
      "用餘票數": 470,
      "選舉人數": 1681,
      "投票率": 72.04000091552734,
      "李順涼": 574,
      "顏清標": 605
    },
    {
      "區別": "烏日區",
      "里別": "仁德里",
      "投票所": 318,
      "有效票數": 1162,
      "無效票數": 31,
      "投票數": 1193,
      "已領未投票數": 0,
      "發出票數": 1193,
      "用餘票數": 385,
      "選舉人數": 1578,
      "投票率": 75.5999984741211,
      "李順涼": 551,
      "顏清標": 611
    },
    {
      "區別": "烏日區",
      "里別": "仁德里",
      "投票所": 319,
      "有效票數": 1204,
      "無效票數": 21,
      "投票數": 1225,
      "已領未投票數": 0,
      "發出票數": 1225,
      "用餘票數": 381,
      "選舉人數": 1606,
      "投票率": 76.27999877929688,
      "李順涼": 514,
      "顏清標": 690
    },
    {
      "區別": "烏日區",
      "里別": "仁德里",
      "投票所": 320,
      "有效票數": 1326,
      "無效票數": 47,
      "投票數": 1373,
      "已領未投票數": 0,
      "發出票數": 1373,
      "用餘票數": 373,
      "選舉人數": 1746,
      "投票率": 78.63999938964844,
      "李順涼": 553,
      "顏清標": 773
    },
    {
      "區別": "烏日區",
      "里別": "仁德里",
      "投票所": 321,
      "有效票數": 1040,
      "無效票數": 34,
      "投票數": 1074,
      "已領未投票數": 0,
      "發出票數": 1074,
      "用餘票數": 305,
      "選舉人數": 1379,
      "投票率": 77.87999725341797,
      "李順涼": 432,
      "顏清標": 608
    },
    {
      "區別": "烏日區",
      "里別": "前竹里",
      "投票所": 322,
      "有效票數": 804,
      "無效票數": 20,
      "投票數": 824,
      "已領未投票數": 0,
      "發出票數": 824,
      "用餘票數": 207,
      "選舉人數": 1031,
      "投票率": 79.91999816894531,
      "李順涼": 403,
      "顏清標": 401
    },
    {
      "區別": "烏日區",
      "里別": "前竹里",
      "投票所": 323,
      "有效票數": 884,
      "無效票數": 21,
      "投票數": 905,
      "已領未投票數": 0,
      "發出票數": 905,
      "用餘票數": 263,
      "選舉人數": 1168,
      "投票率": 77.4800033569336,
      "李順涼": 491,
      "顏清標": 393
    },
    {
      "區別": "烏日區",
      "里別": "五光里",
      "投票所": 324,
      "有效票數": 1152,
      "無效票數": 44,
      "投票數": 1196,
      "已領未投票數": 0,
      "發出票數": 1196,
      "用餘票數": 354,
      "選舉人數": 1550,
      "投票率": 77.16000366210938,
      "李順涼": 450,
      "顏清標": 702
    },
    {
      "區別": "烏日區",
      "里別": "光明里",
      "投票所": 325,
      "有效票數": 634,
      "無效票數": 24,
      "投票數": 658,
      "已領未投票數": 0,
      "發出票數": 658,
      "用餘票數": 180,
      "選舉人數": 838,
      "投票率": 78.5199966430664,
      "李順涼": 336,
      "顏清標": 298
    },
    {
      "區別": "烏日區",
      "里別": "光明里",
      "投票所": 326,
      "有效票數": 879,
      "無效票數": 14,
      "投票數": 893,
      "已領未投票數": 0,
      "發出票數": 893,
      "用餘票數": 267,
      "選舉人數": 1160,
      "投票率": 76.9800033569336,
      "李順涼": 399,
      "顏清標": 480
    },
    {
      "區別": "烏日區",
      "里別": "東園里",
      "投票所": 327,
      "有效票數": 1357,
      "無效票數": 31,
      "投票數": 1388,
      "已領未投票數": 0,
      "發出票數": 1388,
      "用餘票數": 395,
      "選舉人數": 1783,
      "投票率": 77.8499984741211,
      "李順涼": 627,
      "顏清標": 730
    },
    {
      "區別": "烏日區",
      "里別": "溪埧里",
      "投票所": 328,
      "有效票數": 972,
      "無效票數": 23,
      "投票數": 995,
      "已領未投票數": 0,
      "發出票數": 995,
      "用餘票數": 260,
      "選舉人數": 1255,
      "投票率": 79.27999877929688,
      "李順涼": 436,
      "顏清標": 536
    },
    {
      "區別": "烏日區",
      "里別": "溪埧里",
      "投票所": 329,
      "有效票數": 917,
      "無效票數": 22,
      "投票數": 939,
      "已領未投票數": 0,
      "發出票數": 939,
      "用餘票數": 272,
      "選舉人數": 1211,
      "投票率": 77.54000091552734,
      "李順涼": 419,
      "顏清標": 498
    },
    {
      "區別": "烏日區",
      "里別": "溪埧里",
      "投票所": 330,
      "有效票數": 1229,
      "無效票數": 29,
      "投票數": 1258,
      "已領未投票數": 0,
      "發出票數": 1258,
      "用餘票數": 356,
      "選舉人數": 1614,
      "投票率": 77.94000244140625,
      "李順涼": 607,
      "顏清標": 622
    },
    {
      "區別": "烏日區",
      "里別": "螺潭里",
      "投票所": 331,
      "有效票數": 1398,
      "無效票數": 33,
      "投票數": 1431,
      "已領未投票數": 0,
      "發出票數": 1431,
      "用餘票數": 350,
      "選舉人數": 1781,
      "投票率": 80.3499984741211,
      "李順涼": 656,
      "顏清標": 742
    },
    {
      "區別": "烏日區",
      "里別": "北里里",
      "投票所": 332,
      "有效票數": 1120,
      "無效票數": 41,
      "投票數": 1161,
      "已領未投票數": 0,
      "發出票數": 1161,
      "用餘票數": 310,
      "選舉人數": 1471,
      "投票率": 78.93000030517578,
      "李順涼": 573,
      "顏清標": 547
    },
    {
      "區別": "烏日區",
      "里別": "南里里",
      "投票所": 333,
      "有效票數": 881,
      "無效票數": 24,
      "投票數": 905,
      "已領未投票數": 0,
      "發出票數": 905,
      "用餘票數": 223,
      "選舉人數": 1128,
      "投票率": 80.2300033569336,
      "李順涼": 360,
      "顏清標": 521
    },
    {
      "區別": "烏日區",
      "里別": "溪尾里",
      "投票所": 334,
      "有效票數": 559,
      "無效票數": 24,
      "投票數": 583,
      "已領未投票數": 0,
      "發出票數": 583,
      "用餘票數": 232,
      "選舉人數": 815,
      "投票率": 71.52999877929688,
      "李順涼": 184,
      "顏清標": 375
    },
    {
      "區別": "霧峰區",
      "里別": "桐林里",
      "投票所": 335,
      "有效票數": 865,
      "無效票數": 18,
      "投票數": 883,
      "已領未投票數": 0,
      "發出票數": 883,
      "用餘票數": 245,
      "選舉人數": 1128,
      "投票率": 78.27999877929688,
      "李順涼": 387,
      "顏清標": 478
    },
    {
      "區別": "霧峰區",
      "里別": "吉峰里",
      "投票所": 336,
      "有效票數": 1334,
      "無效票數": 53,
      "投票數": 1387,
      "已領未投票數": 0,
      "發出票數": 1387,
      "用餘票數": 593,
      "選舉人數": 1980,
      "投票率": 70.05000305175781,
      "李順涼": 621,
      "顏清標": 713
    },
    {
      "區別": "霧峰區",
      "里別": "吉峰里",
      "投票所": 337,
      "有效票數": 1108,
      "無效票數": 20,
      "投票數": 1128,
      "已領未投票數": 0,
      "發出票數": 1128,
      "用餘票數": 398,
      "選舉人數": 1526,
      "投票率": 73.91999816894531,
      "李順涼": 523,
      "顏清標": 585
    },
    {
      "區別": "霧峰區",
      "里別": "吉峰里",
      "投票所": 338,
      "有效票數": 899,
      "無效票數": 27,
      "投票數": 926,
      "已領未投票數": 0,
      "發出票數": 926,
      "用餘票數": 312,
      "選舉人數": 1238,
      "投票率": 74.80000305175781,
      "李順涼": 339,
      "顏清標": 560
    },
    {
      "區別": "霧峰區",
      "里別": "吉峰里",
      "投票所": 339,
      "有效票數": 1237,
      "無效票數": 42,
      "投票數": 1279,
      "已領未投票數": 0,
      "發出票數": 1279,
      "用餘票數": 398,
      "選舉人數": 1677,
      "投票率": 76.2699966430664,
      "李順涼": 519,
      "顏清標": 718
    },
    {
      "區別": "霧峰區",
      "里別": "吉峰里",
      "投票所": 340,
      "有效票數": 1167,
      "無效票數": 26,
      "投票數": 1193,
      "已領未投票數": 0,
      "發出票數": 1193,
      "用餘票數": 410,
      "選舉人數": 1603,
      "投票率": 74.41999816894531,
      "李順涼": 473,
      "顏清標": 694
    },
    {
      "區別": "霧峰區",
      "里別": "甲寅里",
      "投票所": 341,
      "有效票數": 1147,
      "無效票數": 33,
      "投票數": 1180,
      "已領未投票數": 0,
      "發出票數": 1180,
      "用餘票數": 315,
      "選舉人數": 1495,
      "投票率": 78.93000030517578,
      "李順涼": 467,
      "顏清標": 680
    },
    {
      "區別": "霧峰區",
      "里別": "甲寅里",
      "投票所": 342,
      "有效票數": 1038,
      "無效票數": 38,
      "投票數": 1076,
      "已領未投票數": 0,
      "發出票數": 1076,
      "用餘票數": 348,
      "選舉人數": 1424,
      "投票率": 75.55999755859375,
      "李順涼": 458,
      "顏清標": 580
    },
    {
      "區別": "霧峰區",
      "里別": "甲寅里",
      "投票所": 343,
      "有效票數": 980,
      "無效票數": 43,
      "投票數": 1023,
      "已領未投票數": 0,
      "發出票數": 1023,
      "用餘票數": 267,
      "選舉人數": 1290,
      "投票率": 79.30000305175781,
      "李順涼": 392,
      "顏清標": 588
    },
    {
      "區別": "霧峰區",
      "里別": "本鄉里",
      "投票所": 344,
      "有效票數": 1519,
      "無效票數": 48,
      "投票數": 1567,
      "已領未投票數": 0,
      "發出票數": 1567,
      "用餘票數": 411,
      "選舉人數": 1978,
      "投票率": 79.22000122070312,
      "李順涼": 678,
      "顏清標": 841
    },
    {
      "區別": "霧峰區",
      "里別": "中正里",
      "投票所": 345,
      "有效票數": 1368,
      "無效票數": 44,
      "投票數": 1412,
      "已領未投票數": 0,
      "發出票數": 1412,
      "用餘票數": 364,
      "選舉人數": 1776,
      "投票率": 79.5,
      "李順涼": 559,
      "顏清標": 809
    },
    {
      "區別": "霧峰區",
      "里別": "錦榮里",
      "投票所": 346,
      "有效票數": 749,
      "無效票數": 26,
      "投票數": 775,
      "已領未投票數": 0,
      "發出票數": 775,
      "用餘票數": 250,
      "選舉人數": 1025,
      "投票率": 75.61000061035156,
      "李順涼": 293,
      "顏清標": 456
    },
    {
      "區別": "霧峰區",
      "里別": "萊園里",
      "投票所": 347,
      "有效票數": 756,
      "無效票數": 25,
      "投票數": 781,
      "已領未投票數": 0,
      "發出票數": 781,
      "用餘票數": 265,
      "選舉人數": 1046,
      "投票率": 74.66999816894531,
      "李順涼": 317,
      "顏清標": 439
    },
    {
      "區別": "霧峰區",
      "里別": "本堂里",
      "投票所": 348,
      "有效票數": 1272,
      "無效票數": 58,
      "投票數": 1330,
      "已領未投票數": 0,
      "發出票數": 1330,
      "用餘票數": 413,
      "選舉人數": 1743,
      "投票率": 76.30999755859375,
      "李順涼": 490,
      "顏清標": 782
    },
    {
      "區別": "霧峰區",
      "里別": "本堂里",
      "投票所": 349,
      "有效票數": 1488,
      "無效票數": 59,
      "投票數": 1547,
      "已領未投票數": 0,
      "發出票數": 1547,
      "用餘票數": 488,
      "選舉人數": 2035,
      "投票率": 76.0199966430664,
      "李順涼": 538,
      "顏清標": 950
    },
    {
      "區別": "霧峰區",
      "里別": "本堂里",
      "投票所": 350,
      "有效票數": 1063,
      "無效票數": 47,
      "投票數": 1110,
      "已領未投票數": 0,
      "發出票數": 1110,
      "用餘票數": 342,
      "選舉人數": 1452,
      "投票率": 76.44999694824219,
      "李順涼": 467,
      "顏清標": 596
    },
    {
      "區別": "霧峰區",
      "里別": "北柳里",
      "投票所": 351,
      "有效票數": 1201,
      "無效票數": 27,
      "投票數": 1228,
      "已領未投票數": 1,
      "發出票數": 1229,
      "用餘票數": 383,
      "選舉人數": 1612,
      "投票率": 76.18000030517578,
      "李順涼": 506,
      "顏清標": 695
    },
    {
      "區別": "霧峰區",
      "里別": "北柳里",
      "投票所": 352,
      "有效票數": 1409,
      "無效票數": 25,
      "投票數": 1434,
      "已領未投票數": 0,
      "發出票數": 1434,
      "用餘票數": 414,
      "選舉人數": 1848,
      "投票率": 77.5999984741211,
      "李順涼": 671,
      "顏清標": 738
    },
    {
      "區別": "霧峰區",
      "里別": "南柳里",
      "投票所": 353,
      "有效票數": 1249,
      "無效票數": 46,
      "投票數": 1295,
      "已領未投票數": 0,
      "發出票數": 1295,
      "用餘票數": 344,
      "選舉人數": 1639,
      "投票率": 79.01000213623047,
      "李順涼": 546,
      "顏清標": 703
    },
    {
      "區別": "霧峰區",
      "里別": "四德里",
      "投票所": 354,
      "有效票數": 808,
      "無效票數": 17,
      "投票數": 825,
      "已領未投票數": 0,
      "發出票數": 825,
      "用餘票數": 238,
      "選舉人數": 1063,
      "投票率": 77.61000061035156,
      "李順涼": 401,
      "顏清標": 407
    },
    {
      "區別": "霧峰區",
      "里別": "四德里",
      "投票所": 355,
      "有效票數": 772,
      "無效票數": 31,
      "投票數": 803,
      "已領未投票數": 0,
      "發出票數": 803,
      "用餘票數": 222,
      "選舉人數": 1025,
      "投票率": 78.33999633789062,
      "李順涼": 409,
      "顏清標": 363
    },
    {
      "區別": "霧峰區",
      "里別": "五福里",
      "投票所": 356,
      "有效票數": 950,
      "無效票數": 32,
      "投票數": 982,
      "已領未投票數": 0,
      "發出票數": 982,
      "用餘票數": 232,
      "選舉人數": 1214,
      "投票率": 80.88999938964844,
      "李順涼": 362,
      "顏清標": 588
    },
    {
      "區別": "霧峰區",
      "里別": "五福里",
      "投票所": 357,
      "有效票數": 1008,
      "無效票數": 27,
      "投票數": 1035,
      "已領未投票數": 0,
      "發出票數": 1035,
      "用餘票數": 246,
      "選舉人數": 1281,
      "投票率": 80.80000305175781,
      "李順涼": 465,
      "顏清標": 543
    },
    {
      "區別": "霧峰區",
      "里別": "丁台里",
      "投票所": 358,
      "有效票數": 870,
      "無效票數": 23,
      "投票數": 893,
      "已領未投票數": 0,
      "發出票數": 893,
      "用餘票數": 204,
      "選舉人數": 1097,
      "投票率": 81.4000015258789,
      "李順涼": 400,
      "顏清標": 470
    },
    {
      "區別": "霧峰區",
      "里別": "丁台里",
      "投票所": 359,
      "有效票數": 792,
      "無效票數": 25,
      "投票數": 817,
      "已領未投票數": 0,
      "發出票數": 817,
      "用餘票數": 224,
      "選舉人數": 1041,
      "投票率": 78.4800033569336,
      "李順涼": 399,
      "顏清標": 393
    },
    {
      "區別": "霧峰區",
      "里別": "北勢里",
      "投票所": 360,
      "有效票數": 1376,
      "無效票數": 49,
      "投票數": 1425,
      "已領未投票數": 0,
      "發出票數": 1425,
      "用餘票數": 355,
      "選舉人數": 1780,
      "投票率": 80.05999755859375,
      "李順涼": 551,
      "顏清標": 825
    },
    {
      "區別": "霧峰區",
      "里別": "南勢里",
      "投票所": 361,
      "有效票數": 895,
      "無效票數": 24,
      "投票數": 919,
      "已領未投票數": 0,
      "發出票數": 919,
      "用餘票數": 286,
      "選舉人數": 1205,
      "投票率": 76.2699966430664,
      "李順涼": 370,
      "顏清標": 525
    },
    {
      "區別": "霧峰區",
      "里別": "萬豐里",
      "投票所": 362,
      "有效票數": 947,
      "無效票數": 22,
      "投票數": 969,
      "已領未投票數": 0,
      "發出票數": 969,
      "用餘票數": 299,
      "選舉人數": 1268,
      "投票率": 76.41999816894531,
      "李順涼": 472,
      "顏清標": 475
    },
    {
      "區別": "霧峰區",
      "里別": "萬豐里",
      "投票所": 363,
      "有效票數": 907,
      "無效票數": 21,
      "投票數": 928,
      "已領未投票數": 0,
      "發出票數": 928,
      "用餘票數": 298,
      "選舉人數": 1226,
      "投票率": 75.69000244140625,
      "李順涼": 399,
      "顏清標": 508
    },
    {
      "區別": "霧峰區",
      "里別": "舊正里",
      "投票所": 364,
      "有效票數": 785,
      "無效票數": 25,
      "投票數": 810,
      "已領未投票數": 0,
      "發出票數": 810,
      "用餘票數": 239,
      "選舉人數": 1049,
      "投票率": 77.22000122070312,
      "李順涼": 308,
      "顏清標": 477
    },
    {
      "區別": "霧峰區",
      "里別": "舊正里",
      "投票所": 365,
      "有效票數": 700,
      "無效票數": 26,
      "投票數": 726,
      "已領未投票數": 0,
      "發出票數": 726,
      "用餘票數": 218,
      "選舉人數": 944,
      "投票率": 76.91000366210938,
      "李順涼": 323,
      "顏清標": 377
    },
    {
      "區別": "霧峰區",
      "里別": "坑口里",
      "投票所": 366,
      "有效票數": 944,
      "無效票數": 23,
      "投票數": 967,
      "已領未投票數": 0,
      "發出票數": 967,
      "用餘票數": 303,
      "選舉人數": 1270,
      "投票率": 76.13999938964844,
      "李順涼": 324,
      "顏清標": 620
    },
    {
      "區別": "霧峰區",
      "里別": "坑口里",
      "投票所": 367,
      "有效票數": 1030,
      "無效票數": 27,
      "投票數": 1057,
      "已領未投票數": 0,
      "發出票數": 1057,
      "用餘票數": 345,
      "選舉人數": 1402,
      "投票率": 75.38999938964844,
      "李順涼": 447,
      "顏清標": 583
    },
    {
      "區別": "霧峰區",
      "里別": "峰谷里",
      "投票所": 368,
      "有效票數": 775,
      "無效票數": 32,
      "投票數": 807,
      "已領未投票數": 0,
      "發出票數": 807,
      "用餘票數": 274,
      "選舉人數": 1081,
      "投票率": 74.6500015258789,
      "李順涼": 337,
      "顏清標": 438
    },
    {
      "區別": "霧峰區",
      "里別": "六股里",
      "投票所": 369,
      "有效票數": 929,
      "無效票數": 37,
      "投票數": 966,
      "已領未投票數": 0,
      "發出票數": 966,
      "用餘票數": 315,
      "選舉人數": 1281,
      "投票率": 75.41000366210938,
      "李順涼": 456,
      "顏清標": 473
    },
    {
      "區別": "霧峰區",
      "里別": "六股里",
      "投票所": 370,
      "有效票數": 733,
      "無效票數": 21,
      "投票數": 754,
      "已領未投票數": 0,
      "發出票數": 754,
      "用餘票數": 196,
      "選舉人數": 950,
      "投票率": 79.37000274658203,
      "李順涼": 358,
      "顏清標": 375
    },
    {
      "區別": "大里區",
      "里別": "東湖里",
      "投票所": 371,
      "有效票數": 1073,
      "無效票數": 42,
      "投票數": 1115,
      "已領未投票數": 0,
      "發出票數": 1115,
      "用餘票數": 410,
      "選舉人數": 1525,
      "投票率": 73.11000061035156,
      "李順涼": 469,
      "顏清標": 604
    },
    {
      "區別": "大里區",
      "里別": "東湖里",
      "投票所": 372,
      "有效票數": 1069,
      "無效票數": 31,
      "投票數": 1100,
      "已領未投票數": 0,
      "發出票數": 1100,
      "用餘票數": 432,
      "選舉人數": 1532,
      "投票率": 71.80000305175781,
      "李順涼": 486,
      "顏清標": 583
    },
    {
      "區別": "大里區",
      "里別": "東湖里",
      "投票所": 373,
      "有效票數": 827,
      "無效票數": 43,
      "投票數": 870,
      "已領未投票數": 0,
      "發出票數": 870,
      "用餘票數": 405,
      "選舉人數": 1275,
      "投票率": 68.23999786376953,
      "李順涼": 368,
      "顏清標": 459
    },
    {
      "區別": "大里區",
      "里別": "東湖里",
      "投票所": 374,
      "有效票數": 1009,
      "無效票數": 28,
      "投票數": 1037,
      "已領未投票數": 0,
      "發出票數": 1037,
      "用餘票數": 317,
      "選舉人數": 1354,
      "投票率": 76.58999633789062,
      "李順涼": 460,
      "顏清標": 549
    },
    {
      "區別": "大里區",
      "里別": "東湖里",
      "投票所": 375,
      "有效票數": 845,
      "無效票數": 39,
      "投票數": 884,
      "已領未投票數": 0,
      "發出票數": 884,
      "用餘票數": 295,
      "選舉人數": 1179,
      "投票率": 74.9800033569336,
      "李順涼": 367,
      "顏清標": 478
    },
    {
      "區別": "大里區",
      "里別": "東湖里",
      "投票所": 376,
      "有效票數": 1039,
      "無效票數": 40,
      "投票數": 1079,
      "已領未投票數": 0,
      "發出票數": 1079,
      "用餘票數": 373,
      "選舉人數": 1452,
      "投票率": 74.30999755859375,
      "李順涼": 501,
      "顏清標": 538
    },
    {
      "區別": "大里區",
      "里別": "西湖里",
      "投票所": 377,
      "有效票數": 953,
      "無效票數": 26,
      "投票數": 979,
      "已領未投票數": 0,
      "發出票數": 979,
      "用餘票數": 255,
      "選舉人數": 1234,
      "投票率": 79.33999633789062,
      "李順涼": 500,
      "顏清標": 453
    },
    {
      "區別": "大里區",
      "里別": "西湖里",
      "投票所": 378,
      "有效票數": 929,
      "無效票數": 27,
      "投票數": 956,
      "已領未投票數": 0,
      "發出票數": 956,
      "用餘票數": 284,
      "選舉人數": 1240,
      "投票率": 77.0999984741211,
      "李順涼": 403,
      "顏清標": 526
    }
  ]
}