{
  "參選人": [
    {
      "姓名": "曾智勇",
      "政黨": "民主進步黨"
    },
    {
      "姓名": "高金素梅",
      "政黨": "無黨團結聯盟"
    },
    {
      "姓名": "邱文生",
      "政黨": "無黨籍及未經政黨推薦"
    },
    {
      "姓名": "孔文吉",
      "政黨": "中國國民黨"
    },
    {
      "姓名": "瓦歷斯‧貝林 Walis‧Perin",
      "政黨": "親民黨"
    },
    {
      "姓名": "簡東明 Uliw．Qaljupayare",
      "政黨": "中國國民黨"
    }
  ],
  "資料": [
    {
      "區別": "臺東市",
      "里別": "文化里",
      "投票所": 1,
      "有效票數": 5,
      "無效票數": 0,
      "投票數": 5,
      "已領未投票數": 0,
      "發出票數": 5,
      "用餘票數": 1,
      "選舉人數": 6,
      "投票率": 83.33000183105469,
      "曾智勇": 0,
      "高金素梅": 2,
      "邱文生": 1,
      "孔文吉": 0,
      "瓦歷斯‧貝林 Walis‧Perin": 0,
      "簡東明 Uliw．Qaljupayare": 2
    },
    {
      "區別": "臺東市",
      "里別": "民族里",
      "投票所": 2,
      "有效票數": 3,
      "無效票數": 0,
      "投票數": 3,
      "已領未投票數": 0,
      "發出票數": 3,
      "用餘票數": 2,
      "選舉人數": 5,
      "投票率": 60,
      "曾智勇": 0,
      "高金素梅": 2,
      "邱文生": 0,
      "孔文吉": 0,
      "瓦歷斯‧貝林 Walis‧Perin": 1,
      "簡東明 Uliw．Qaljupayare": 0
    },
    {
      "區別": "臺東市",
      "里別": "自強里",
      "投票所": 3,
      "有效票數": 5,
      "無效票數": 0,
      "投票數": 5,
      "已領未投票數": 0,
      "發出票數": 5,
      "用餘票數": 0,
      "選舉人數": 5,
      "投票率": 100,
      "曾智勇": 0,
      "高金素梅": 0,
      "邱文生": 0,
      "孔文吉": 2,
      "瓦歷斯‧貝林 Walis‧Perin": 1,
      "簡東明 Uliw．Qaljupayare": 2
    },
    {
      "區別": "臺東市",
      "里別": "自強里",
      "投票所": 4,
      "有效票數": 9,
      "無效票數": 0,
      "投票數": 9,
      "已領未投票數": 0,
      "發出票數": 9,
      "用餘票數": 4,
      "選舉人數": 13,
      "投票率": 69.2300033569336,
      "曾智勇": 1,
      "高金素梅": 0,
      "邱文生": 0,
      "孔文吉": 3,
      "瓦歷斯‧貝林 Walis‧Perin": 2,
      "簡東明 Uliw．Qaljupayare": 3
    },
    {
      "區別": "臺東市",
      "里別": "自強里",
      "投票所": 5,
      "有效票數": 3,
      "無效票數": 0,
      "投票數": 3,
      "已領未投票數": 0,
      "發出票數": 3,
      "用餘票數": 1,
      "選舉人數": 4,
      "投票率": 75,
      "曾智勇": 0,
      "高金素梅": 1,
      "邱文生": 0,
      "孔文吉": 1,
      "瓦歷斯‧貝林 Walis‧Perin": 1,
      "簡東明 Uliw．Qaljupayare": 0
    },
    {
      "區別": "臺東市",
      "里別": "民生里",
      "投票所": 6,
      "有效票數": 8,
      "無效票數": 0,
      "投票數": 8,
      "已領未投票數": 0,
      "發出票數": 8,
      "用餘票數": 1,
      "選舉人數": 9,
      "投票率": 88.88999938964844,
      "曾智勇": 0,
      "高金素梅": 2,
      "邱文生": 0,
      "孔文吉": 2,
      "瓦歷斯‧貝林 Walis‧Perin": 1,
      "簡東明 Uliw．Qaljupayare": 3
    },
    {
      "區別": "臺東市",
      "里別": "民生里",
      "投票所": 7,
      "有效票數": 2,
      "無效票數": 1,
      "投票數": 3,
      "已領未投票數": 0,
      "發出票數": 3,
      "用餘票數": 1,
      "選舉人數": 4,
      "投票率": 75,
      "曾智勇": 0,
      "高金素梅": 1,
      "邱文生": 0,
      "孔文吉": 0,
      "瓦歷斯‧貝林 Walis‧Perin": 0,
      "簡東明 Uliw．Qaljupayare": 1
    },
    {
      "區別": "臺東市",
      "里別": "寶桑里",
      "投票所": 8,
      "有效票數": 12,
      "無效票數": 0,
      "投票數": 12,
      "已領未投票數": 0,
      "發出票數": 12,
      "用餘票數": 3,
      "選舉人數": 15,
      "投票率": 80,
      "曾智勇": 0,
      "高金素梅": 3,
      "邱文生": 0,
      "孔文吉": 2,
      "瓦歷斯‧貝林 Walis‧Perin": 2,
      "簡東明 Uliw．Qaljupayare": 5
    },
    {
      "區別": "臺東市",
      "里別": "民權里",
      "投票所": 9,
      "有效票數": 7,
      "無效票數": 0,
      "投票數": 7,
      "已領未投票數": 0,
      "發出票數": 7,
      "用餘票數": 4,
      "選舉人數": 11,
      "投票率": 63.63999938964844,
      "曾智勇": 2,
      "高金素梅": 0,
      "邱文生": 0,
      "孔文吉": 0,
      "瓦歷斯‧貝林 Walis‧Perin": 5,
      "簡東明 Uliw．Qaljupayare": 0
    },
    {
      "區別": "臺東市",
      "里別": "四維里",
      "投票所": 10,
      "有效票數": 3,
      "無效票數": 0,
      "投票數": 3,
      "已領未投票數": 0,
      "發出票數": 3,
      "用餘票數": 3,
      "選舉人數": 6,
      "投票率": 50,
      "曾智勇": 0,
      "高金素梅": 0,
      "邱文生": 0,
      "孔文吉": 1,
      "瓦歷斯‧貝林 Walis‧Perin": 0,
      "簡東明 Uliw．Qaljupayare": 2
    },
    {
      "區別": "臺東市",
      "里別": "中華里",
      "投票所": 11,
      "有效票數": 11,
      "無效票數": 0,
      "投票數": 11,
      "已領未投票數": 0,
      "發出票數": 11,
      "用餘票數": 3,
      "選舉人數": 14,
      "投票率": 78.56999969482422,
      "曾智勇": 0,
      "高金素梅": 1,
      "邱文生": 0,
      "孔文吉": 2,
      "瓦歷斯‧貝林 Walis‧Perin": 3,
      "簡東明 Uliw．Qaljupayare": 5
    },
    {
      "區別": "臺東市",
      "里別": "仁愛里",
      "投票所": 12,
      "有效票數": 0,
      "無效票數": 0,
      "投票數": 0,
      "已領未投票數": 0,
      "發出票數": 0,
      "用餘票數": 2,
      "選舉人數": 2,
      "投票率": 0,
      "曾智勇": 0,
      "高金素梅": 0,
      "邱文生": 0,
      "孔文吉": 0,
      "瓦歷斯‧貝林 Walis‧Perin": 0,
      "簡東明 Uliw．Qaljupayare": 0
    },
    {
      "區別": "臺東市",
      "里別": "強國里",
      "投票所": 13,
      "有效票數": 5,
      "無效票數": 0,
      "投票數": 5,
      "已領未投票數": 0,
      "發出票數": 5,
      "用餘票數": 1,
      "選舉人數": 6,
      "投票率": 83.33000183105469,
      "曾智勇": 0,
      "高金素梅": 1,
      "邱文生": 1,
      "孔文吉": 2,
      "瓦歷斯‧貝林 Walis‧Perin": 0,
      "簡東明 Uliw．Qaljupayare": 1
    },
    {
      "區別": "臺東市",
      "里別": "大同里",
      "投票所": 14,
      "有效票數": 2,
      "無效票數": 0,
      "投票數": 2,
      "已領未投票數": 0,
      "發出票數": 2,
      "用餘票數": 1,
      "選舉人數": 3,
      "投票率": 66.66999816894531,
      "曾智勇": 0,
      "高金素梅": 1,
      "邱文生": 0,
      "孔文吉": 0,
      "瓦歷斯‧貝林 Walis‧Perin": 1,
      "簡東明 Uliw．Qaljupayare": 0
    },
    {
      "區別": "臺東市",
      "里別": "成功里",
      "投票所": 15,
      "有效票數": 2,
      "無效票數": 0,
      "投票數": 2,
      "已領未投票數": 0,
      "發出票數": 2,
      "用餘票數": 1,
      "選舉人數": 3,
      "投票率": 66.66999816894531,
      "曾智勇": 0,
      "高金素梅": 1,
      "邱文生": 0,
      "孔文吉": 0,
      "瓦歷斯‧貝林 Walis‧Perin": 0,
      "簡東明 Uliw．Qaljupayare": 1
    },
    {
      "區別": "臺東市",
      "里別": "建國里",
      "投票所": 16,
      "有效票數": 10,
      "無效票數": 0,
      "投票數": 10,
      "已領未投票數": 0,
      "發出票數": 10,
      "用餘票數": 3,
      "選舉人數": 13,
      "投票率": 76.91999816894531,
      "曾智勇": 0,
      "高金素梅": 1,
      "邱文生": 0,
      "孔文吉": 6,
      "瓦歷斯‧貝林 Walis‧Perin": 1,
      "簡東明 Uliw．Qaljupayare": 2
    },
    {
      "區別": "臺東市",
      "里別": "中正里",
      "投票所": 17,
      "有效票數": 1,
      "無效票數": 0,
      "投票數": 1,
      "已領未投票數": 0,
      "發出票數": 1,
      "用餘票數": 1,
      "選舉人數": 2,
      "投票率": 50,
      "曾智勇": 0,
      "高金素梅": 0,
      "邱文生": 0,
      "孔文吉": 1,
      "瓦歷斯‧貝林 Walis‧Perin": 0,
      "簡東明 Uliw．Qaljupayare": 0
    },
    {
      "區別": "臺東市",
      "里別": "中山里",
      "投票所": 18,
      "有效票數": 0,
      "無效票數": 0,
      "投票數": 0,
      "已領未投票數": 0,
      "發出票數": 0,
      "用餘票數": 0,
      "選舉人數": 0,
      "投票率": 0,
      "曾智勇": 0,
      "高金素梅": 0,
      "邱文生": 0,
      "孔文吉": 0,
      "瓦歷斯‧貝林 Walis‧Perin": 0,
      "簡東明 Uliw．Qaljupayare": 0
    },
    {
      "區別": "臺東市",
      "里別": "興國里",
      "投票所": 19,
      "有效票數": 3,
      "無效票數": 0,
      "投票數": 3,
      "已領未投票數": 0,
      "發出票數": 3,
      "用餘票數": 1,
      "選舉人數": 4,
      "投票率": 75,
      "曾智勇": 0,
      "高金素梅": 0,
      "邱文生": 0,
      "孔文吉": 0,
      "瓦歷斯‧貝林 Walis‧Perin": 2,
      "簡東明 Uliw．Qaljupayare": 1
    },
    {
      "區別": "臺東市",
      "里別": "鐵花里",
      "投票所": 20,
      "有效票數": 2,
      "無效票數": 0,
      "投票數": 2,
      "已領未投票數": 0,
      "發出票數": 2,
      "用餘票數": 0,
      "選舉人數": 2,
      "投票率": 100,
      "曾智勇": 1,
      "高金素梅": 1,
      "邱文生": 0,
      "孔文吉": 0,
      "瓦歷斯‧貝林 Walis‧Perin": 0,
      "簡東明 Uliw．Qaljupayare": 0
    },
    {
      "區別": "臺東市",
      "里別": "東海里",
      "投票所": 21,
      "有效票數": 16,
      "無效票數": 0,
      "投票數": 16,
      "已領未投票數": 0,
      "發出票數": 16,
      "用餘票數": 7,
      "選舉人數": 23,
      "投票率": 69.56999969482422,
      "曾智勇": 2,
      "高金素梅": 8,
      "邱文生": 0,
      "孔文吉": 4,
      "瓦歷斯‧貝林 Walis‧Perin": 0,
      "簡東明 Uliw．Qaljupayare": 2
    },
    {
      "區別": "臺東市",
      "里別": "東海里",
      "投票所": 22,
      "有效票數": 10,
      "無效票數": 0,
      "投票數": 10,
      "已領未投票數": 0,
      "發出票數": 10,
      "用餘票數": 3,
      "選舉人數": 13,
      "投票率": 76.91999816894531,
      "曾智勇": 0,
      "高金素梅": 2,
      "邱文生": 0,
      "孔文吉": 5,
      "瓦歷斯‧貝林 Walis‧Perin": 1,
      "簡東明 Uliw．Qaljupayare": 2
    },
    {
      "區別": "臺東市",
      "里別": "復國里",
      "投票所": 23,
      "有效票數": 1,
      "無效票數": 0,
      "投票數": 1,
      "已領未投票數": 0,
      "發出票數": 1,
      "用餘票數": 0,
      "選舉人數": 1,
      "投票率": 100,
      "曾智勇": 0,
      "高金素梅": 1,
      "邱文生": 0,
      "孔文吉": 0,
      "瓦歷斯‧貝林 Walis‧Perin": 0,
      "簡東明 Uliw．Qaljupayare": 0
    },
    {
      "區別": "臺東市",
      "里別": "復興里",
      "投票所": 24,
      "有效票數": 0,
      "無效票數": 0,
      "投票數": 0,
      "已領未投票數": 0,
      "發出票數": 0,
      "用餘票數": 0,
      "選舉人數": 0,
      "投票率": 0,
      "曾智勇": 0,
      "高金素梅": 0,
      "邱文生": 0,
      "孔文吉": 0,
      "瓦歷斯‧貝林 Walis‧Perin": 0,
      "簡東明 Uliw．Qaljupayare": 0
    },
    {
      "區別": "臺東市",
      "里別": "新興里",
      "投票所": 25,
      "有效票數": 2,
      "無效票數": 0,
      "投票數": 2,
      "已領未投票數": 0,
      "發出票數": 2,
      "用餘票數": 0,
      "選舉人數": 2,
      "投票率": 100,
      "曾智勇": 0,
      "高金素梅": 0,
      "邱文生": 0,
      "孔文吉": 0,
      "瓦歷斯‧貝林 Walis‧Perin": 2,
      "簡東明 Uliw．Qaljupayare": 0
    },
    {
      "區別": "臺東市",
      "里別": "新生里",
      "投票所": 26,
      "有效票數": 7,
      "無效票數": 0,
      "投票數": 7,
      "已領未投票數": 0,
      "發出票數": 7,
      "用餘票數": 7,
      "選舉人數": 14,
      "投票率": 50,
      "曾智勇": 2,
      "高金素梅": 1,
      "邱文生": 0,
      "孔文吉": 0,
      "瓦歷斯‧貝林 Walis‧Perin": 1,
      "簡東明 Uliw．Qaljupayare": 3
    },
    {
      "區別": "臺東市",
      "里別": "新生里",
      "投票所": 27,
      "有效票數": 6,
      "無效票數": 0,
      "投票數": 6,
      "已領未投票數": 0,
      "發出票數": 6,
      "用餘票數": 0,
      "選舉人數": 6,
      "投票率": 100,
      "曾智勇": 0,
      "高金素梅": 0,
      "邱文生": 0,
      "孔文吉": 1,
      "瓦歷斯‧貝林 Walis‧Perin": 1,
      "簡東明 Uliw．Qaljupayare": 4
    },
    {
      "區別": "臺東市",
      "里別": "新生里",
      "投票所": 28,
      "有效票數": 12,
      "無效票數": 0,
      "投票數": 12,
      "已領未投票數": 0,
      "發出票數": 12,
      "用餘票數": 6,
      "選舉人數": 18,
      "投票率": 66.66999816894531,
      "曾智勇": 0,
      "高金素梅": 0,
      "邱文生": 0,
      "孔文吉": 6,
      "瓦歷斯‧貝林 Walis‧Perin": 1,
      "簡東明 Uliw．Qaljupayare": 5
    },
    {
      "區別": "臺東市",
      "里別": "新生里",
      "投票所": 29,
      "有效票數": 17,
      "無效票數": 0,
      "投票數": 17,
      "已領未投票數": 0,
      "發出票數": 17,
      "用餘票數": 8,
      "選舉人數": 25,
      "投票率": 68,
      "曾智勇": 0,
      "高金素梅": 8,
      "邱文生": 0,
      "孔文吉": 4,
      "瓦歷斯‧貝林 Walis‧Perin": 3,
      "簡東明 Uliw．Qaljupayare": 2
    },
    {
      "區別": "臺東市",
      "里別": "中心里",
      "投票所": 30,
      "有效票數": 16,
      "無效票數": 0,
      "投票數": 16,
      "已領未投票數": 0,
      "發出票數": 16,
      "用餘票數": 9,
      "選舉人數": 25,
      "投票率": 64,
      "曾智勇": 3,
      "高金素梅": 4,
      "邱文生": 0,
      "孔文吉": 3,
      "瓦歷斯‧貝林 Walis‧Perin": 5,
      "簡東明 Uliw．Qaljupayare": 1
    },
    {
      "區別": "臺東市",
      "里別": "中心里",
      "投票所": 31,
      "有效票數": 14,
      "無效票數": 0,
      "投票數": 14,
      "已領未投票數": 0,
      "發出票數": 14,
      "用餘票數": 3,
      "選舉人數": 17,
      "投票率": 82.3499984741211,
      "曾智勇": 0,
      "高金素梅": 3,
      "邱文生": 0,
      "孔文吉": 4,
      "瓦歷斯‧貝林 Walis‧Perin": 2,
      "簡東明 Uliw．Qaljupayare": 5
    },
    {
      "區別": "臺東市",
      "里別": "馬蘭里",
      "投票所": 32,
      "有效票數": 6,
      "無效票數": 0,
      "投票數": 6,
      "已領未投票數": 0,
      "發出票數": 6,
      "用餘票數": 5,
      "選舉人數": 11,
      "投票率": 54.54999923706055,
      "曾智勇": 0,
      "高金素梅": 2,
      "邱文生": 0,
      "孔文吉": 2,
      "瓦歷斯‧貝林 Walis‧Perin": 0,
      "簡東明 Uliw．Qaljupayare": 2
    },
    {
      "區別": "臺東市",
      "里別": "馬蘭里",
      "投票所": 33,
      "有效票數": 14,
      "無效票數": 0,
      "投票數": 14,
      "已領未投票數": 0,
      "發出票數": 14,
      "用餘票數": 4,
      "選舉人數": 18,
      "投票率": 77.77999877929688,
      "曾智勇": 1,
      "高金素梅": 6,
      "邱文生": 1,
      "孔文吉": 3,
      "瓦歷斯‧貝林 Walis‧Perin": 0,
      "簡東明 Uliw．Qaljupayare": 3
    },
    {
      "區別": "臺東市",
      "里別": "光明里",
      "投票所": 34,
      "有效票數": 12,
      "無效票數": 0,
      "投票數": 12,
      "已領未投票數": 0,
      "發出票數": 12,
      "用餘票數": 7,
      "選舉人數": 19,
      "投票率": 63.15999984741211,
      "曾智勇": 0,
      "高金素梅": 3,
      "邱文生": 0,
      "孔文吉": 4,
      "瓦歷斯‧貝林 Walis‧Perin": 0,
      "簡東明 Uliw．Qaljupayare": 5
    },
    {
      "區別": "臺東市",
      "里別": "光明里",
      "投票所": 35,
      "有效票數": 23,
      "無效票數": 0,
      "投票數": 23,
      "已領未投票數": 0,
      "發出票數": 23,
      "用餘票數": 11,
      "選舉人數": 34,
      "投票率": 67.6500015258789,
      "曾智勇": 0,
      "高金素梅": 6,
      "邱文生": 0,
      "孔文吉": 9,
      "瓦歷斯‧貝林 Walis‧Perin": 2,
      "簡東明 Uliw．Qaljupayare": 6
    },
    {
      "區別": "臺東市",
      "里別": "豐年里",
      "投票所": 36,
      "有效票數": 9,
      "無效票數": 0,
      "投票數": 9,
      "已領未投票數": 0,
      "發出票數": 9,
      "用餘票數": 7,
      "選舉人數": 16,
      "投票率": 56.25,
      "曾智勇": 0,
      "高金素梅": 2,
      "邱文生": 0,
      "孔文吉": 1,
      "瓦歷斯‧貝林 Walis‧Perin": 1,
      "簡東明 Uliw．Qaljupayare": 5
    },
    {
      "區別": "臺東市",
      "里別": "豐年里",
      "投票所": 37,
      "有效票數": 24,
      "無效票數": 1,
      "投票數": 25,
      "已領未投票數": 0,
      "發出票數": 25,
      "用餘票數": 13,
      "選舉人數": 38,
      "投票率": 65.79000091552734,
      "曾智勇": 1,
      "高金素梅": 6,
      "邱文生": 0,
      "孔文吉": 6,
      "瓦歷斯‧貝林 Walis‧Perin": 2,
      "簡東明 Uliw．Qaljupayare": 9
    },
    {
      "區別": "臺東市",
      "里別": "豐樂里",
      "投票所": 38,
      "有效票數": 10,
      "無效票數": 0,
      "投票數": 10,
      "已領未投票數": 0,
      "發出票數": 10,
      "用餘票數": 8,
      "選舉人數": 18,
      "投票率": 55.560001373291016,
      "曾智勇": 0,
      "高金素梅": 3,
      "邱文生": 0,
      "孔文吉": 3,
      "瓦歷斯‧貝林 Walis‧Perin": 0,
      "簡東明 Uliw．Qaljupayare": 4
    },
    {
      "區別": "臺東市",
      "里別": "永樂里",
      "投票所": 39,
      "有效票數": 27,
      "無效票數": 0,
      "投票數": 27,
      "已領未投票數": 0,
      "發出票數": 27,
      "用餘票數": 11,
      "選舉人數": 38,
      "投票率": 71.05000305175781,
      "曾智勇": 0,
      "高金素梅": 5,
      "邱文生": 0,
      "孔文吉": 7,
      "瓦歷斯‧貝林 Walis‧Perin": 5,
      "簡東明 Uliw．Qaljupayare": 10
    },
    {
      "區別": "臺東市",
      "里別": "康樂里",
      "投票所": 40,
      "有效票數": 10,
      "無效票數": 1,
      "投票數": 11,
      "已領未投票數": 0,
      "發出票數": 11,
      "用餘票數": 2,
      "選舉人數": 13,
      "投票率": 84.62000274658203,
      "曾智勇": 0,
      "高金素梅": 0,
      "邱文生": 0,
      "孔文吉": 6,
      "瓦歷斯‧貝林 Walis‧Perin": 1,
      "簡東明 Uliw．Qaljupayare": 3
    },
    {
      "區別": "臺東市",
      "里別": "豐榮里",
      "投票所": 41,
      "有效票數": 11,
      "無效票數": 0,
      "投票數": 11,
      "已領未投票數": 0,
      "發出票數": 11,
      "用餘票數": 1,
      "選舉人數": 12,
      "投票率": 91.66999816894531,
      "曾智勇": 0,
      "高金素梅": 2,
      "邱文生": 0,
      "孔文吉": 5,
      "瓦歷斯‧貝林 Walis‧Perin": 0,
      "簡東明 Uliw．Qaljupayare": 4
    },
    {
      "區別": "臺東市",
      "里別": "豐榮里",
      "投票所": 42,
      "有效票數": 8,
      "無效票數": 0,
      "投票數": 8,
      "已領未投票數": 0,
      "發出票數": 8,
      "用餘票數": 4,
      "選舉人數": 12,
      "投票率": 66.66999816894531,
      "曾智勇": 0,
      "高金素梅": 3,
      "邱文生": 0,
      "孔文吉": 1,
      "瓦歷斯‧貝林 Walis‧Perin": 1,
      "簡東明 Uliw．Qaljupayare": 3
    },
    {
      "區別": "臺東市",
      "里別": "豐榮里",
      "投票所": 43,
      "有效票數": 4,
      "無效票數": 0,
      "投票數": 4,
      "已領未投票數": 0,
      "發出票數": 4,
      "用餘票數": 4,
      "選舉人數": 8,
      "投票率": 50,
      "曾智勇": 0,
      "高金素梅": 2,
      "邱文生": 0,
      "孔文吉": 0,
      "瓦歷斯‧貝林 Walis‧Perin": 1,
      "簡東明 Uliw．Qaljupayare": 1
    },
    {
      "區別": "臺東市",
      "里別": "豐榮里",
      "投票所": 44,
      "有效票數": 13,
      "無效票數": 1,
      "投票數": 14,
      "已領未投票數": 0,
      "發出票數": 14,
      "用餘票數": 3,
      "選舉人數": 17,
      "投票率": 82.3499984741211,
      "曾智勇": 0,
      "高金素梅": 2,
      "邱文生": 0,
      "孔文吉": 0,
      "瓦歷斯‧貝林 Walis‧Perin": 3,
      "簡東明 Uliw．Qaljupayare": 8
    },
    {
      "區別": "臺東市",
      "里別": "豐榮里",
      "投票所": 45,
      "有效票數": 34,
      "無效票數": 2,
      "投票數": 36,
      "已領未投票數": 0,
      "發出票數": 36,
      "用餘票數": 15,
      "選舉人數": 51,
      "投票率": 70.58999633789062,
      "曾智勇": 3,
      "高金素梅": 4,
      "邱文生": 1,
      "孔文吉": 9,
      "瓦歷斯‧貝林 Walis‧Perin": 2,
      "簡東明 Uliw．Qaljupayare": 15
    },
    {
      "區別": "臺東市",
      "里別": "豐谷里",
      "投票所": 46,
      "有效票數": 14,
      "無效票數": 1,
      "投票數": 15,
      "已領未投票數": 0,
      "發出票數": 15,
      "用餘票數": 12,
      "選舉人數": 27,
      "投票率": 55.560001373291016,
      "曾智勇": 0,
      "高金素梅": 2,
      "邱文生": 0,
      "孔文吉": 4,
      "瓦歷斯‧貝林 Walis‧Perin": 3,
      "簡東明 Uliw．Qaljupayare": 5
    },
    {
      "區別": "臺東市",
      "里別": "豐谷里",
      "投票所": 47,
      "有效票數": 7,
      "無效票數": 0,
      "投票數": 7,
      "已領未投票數": 0,
      "發出票數": 7,
      "用餘票數": 3,
      "選舉人數": 10,
      "投票率": 70,
      "曾智勇": 1,
      "高金素梅": 1,
      "邱文生": 0,
      "孔文吉": 1,
      "瓦歷斯‧貝林 Walis‧Perin": 0,
      "簡東明 Uliw．Qaljupayare": 4
    },
    {
      "區別": "臺東市",
      "里別": "豐谷里",
      "投票所": 48,
      "有效票數": 9,
      "無效票數": 3,
      "投票數": 12,
      "已領未投票數": 0,
      "發出票數": 12,
      "用餘票數": 5,
      "選舉人數": 17,
      "投票率": 70.58999633789062,
      "曾智勇": 0,
      "高金素梅": 3,
      "邱文生": 0,
      "孔文吉": 3,
      "瓦歷斯‧貝林 Walis‧Perin": 1,
      "簡東明 Uliw．Qaljupayare": 2
    },
    {
      "區別": "臺東市",
      "里別": "豐里里",
      "投票所": 49,
      "有效票數": 4,
      "無效票數": 0,
      "投票數": 4,
      "已領未投票數": 0,
      "發出票數": 4,
      "用餘票數": 1,
      "選舉人數": 5,
      "投票率": 80,
      "曾智勇": 0,
      "高金素梅": 0,
      "邱文生": 0,
      "孔文吉": 1,
      "瓦歷斯‧貝林 Walis‧Perin": 1,
      "簡東明 Uliw．Qaljupayare": 2
    },
    {
      "區別": "臺東市",
      "里別": "豐里里",
      "投票所": 50,
      "有效票數": 6,
      "無效票數": 1,
      "投票數": 7,
      "已領未投票數": 0,
      "發出票數": 7,
      "用餘票數": 5,
      "選舉人數": 12,
      "投票率": 58.33000183105469,
      "曾智勇": 0,
      "高金素梅": 0,
      "邱文生": 0,
      "孔文吉": 2,
      "瓦歷斯‧貝林 Walis‧Perin": 1,
      "簡東明 Uliw．Qaljupayare": 3
    },
    {
      "區別": "臺東市",
      "里別": "豐原里",
      "投票所": 51,
      "有效票數": 2,
      "無效票數": 0,
      "投票數": 2,
      "已領未投票數": 0,
      "發出票數": 2,
      "用餘票數": 2,
      "選舉人數": 4,
      "投票率": 50,
      "曾智勇": 0,
      "高金素梅": 1,
      "邱文生": 0,
      "孔文吉": 0,
      "瓦歷斯‧貝林 Walis‧Perin": 0,
      "簡東明 Uliw．Qaljupayare": 1
    },
    {
      "區別": "臺東市",
      "里別": "富岡里",
      "投票所": 52,
      "有效票數": 2,
      "無效票數": 0,
      "投票數": 2,
      "已領未投票數": 0,
      "發出票數": 2,
      "用餘票數": 3,
      "選舉人數": 5,
      "投票率": 40,
      "曾智勇": 0,
      "高金素梅": 0,
      "邱文生": 0,
      "孔文吉": 1,
      "瓦歷斯‧貝林 Walis‧Perin": 0,
      "簡東明 Uliw．Qaljupayare": 1
    },
    {
      "區別": "臺東市",
      "里別": "富豐里",
      "投票所": 53,
      "有效票數": 5,
      "無效票數": 0,
      "投票數": 5,
      "已領未投票數": 0,
      "發出票數": 5,
      "用餘票數": 3,
      "選舉人數": 8,
      "投票率": 62.5,
      "曾智勇": 0,
      "高金素梅": 1,
      "邱文生": 0,
      "孔文吉": 1,
      "瓦歷斯‧貝林 Walis‧Perin": 1,
      "簡東明 Uliw．Qaljupayare": 2
    },
    {
      "區別": "臺東市",
      "里別": "南榮里",
      "投票所": 54,
      "有效票數": 7,
      "無效票數": 0,
      "投票數": 7,
      "已領未投票數": 0,
      "發出票數": 7,
      "用餘票數": 2,
      "選舉人數": 9,
      "投票率": 77.77999877929688,
      "曾智勇": 0,
      "高金素梅": 2,
      "邱文生": 0,
      "孔文吉": 4,
      "瓦歷斯‧貝林 Walis‧Perin": 0,
      "簡東明 Uliw．Qaljupayare": 1
    },
    {
      "區別": "臺東市",
      "里別": "南榮里",
      "投票所": 55,
      "有效票數": 19,
      "無效票數": 0,
      "投票數": 19,
      "已領未投票數": 0,
      "發出票數": 19,
      "用餘票數": 9,
      "選舉人數": 28,
      "投票率": 67.86000061035156,
      "曾智勇": 0,
      "高金素梅": 5,
      "邱文生": 0,
      "孔文吉": 7,
      "瓦歷斯‧貝林 Walis‧Perin": 3,
      "簡東明 Uliw．Qaljupayare": 4
    },
    {
      "區別": "臺東市",
      "里別": "岩灣里",
      "投票所": 56,
      "有效票數": 24,
      "無效票數": 2,
      "投票數": 26,
      "已領未投票數": 0,
      "發出票數": 26,
      "用餘票數": 15,
      "選舉人數": 41,
      "投票率": 63.40999984741211,
      "曾智勇": 0,
      "高金素梅": 6,
      "邱文生": 0,
      "孔文吉": 12,
      "瓦歷斯‧貝林 Walis‧Perin": 1,
      "簡東明 Uliw．Qaljupayare": 5
    },
    {
      "區別": "臺東市",
      "里別": "卑南里",
      "投票所": 57,
      "有效票數": 20,
      "無效票數": 1,
      "投票數": 21,
      "已領未投票數": 0,
      "發出票數": 21,
      "用餘票數": 5,
      "選舉人數": 26,
      "投票率": 80.7699966430664,
      "曾智勇": 2,
      "高金素梅": 7,
      "邱文生": 1,
      "孔文吉": 4,
      "瓦歷斯‧貝林 Walis‧Perin": 2,
      "簡東明 Uliw．Qaljupayare": 4
    },
    {
      "區別": "臺東市",
      "里別": "卑南里",
      "投票所": 58,
      "有效票數": 3,
      "無效票數": 0,
      "投票數": 3,
      "已領未投票數": 0,
      "發出票數": 3,
      "用餘票數": 4,
      "選舉人數": 7,
      "投票率": 42.86000061035156,
      "曾智勇": 0,
      "高金素梅": 0,
      "邱文生": 0,
      "孔文吉": 1,
      "瓦歷斯‧貝林 Walis‧Perin": 1,
      "簡東明 Uliw．Qaljupayare": 1
    },
    {
      "區別": "臺東市",
      "里別": "南王里",
      "投票所": 59,
      "有效票數": 14,
      "無效票數": 0,
      "投票數": 14,
      "已領未投票數": 0,
      "發出票數": 14,
      "用餘票數": 7,
      "選舉人數": 21,
      "投票率": 66.66999816894531,
      "曾智勇": 1,
      "高金素梅": 5,
      "邱文生": 0,
      "孔文吉": 5,
      "瓦歷斯‧貝林 Walis‧Perin": 2,
      "簡東明 Uliw．Qaljupayare": 1
    },
    {
      "區別": "臺東市",
      "里別": "南王里",
      "投票所": 60,
      "有效票數": 14,
      "無效票數": 0,
      "投票數": 14,
      "已領未投票數": 0,
      "發出票數": 14,
      "用餘票數": 8,
      "選舉人數": 22,
      "投票率": 63.63999938964844,
      "曾智勇": 0,
      "高金素梅": 3,
      "邱文生": 0,
      "孔文吉": 5,
      "瓦歷斯‧貝林 Walis‧Perin": 3,
      "簡東明 Uliw．Qaljupayare": 3
    },
    {
      "區別": "臺東市",
      "里別": "豐田里",
      "投票所": 61,
      "有效票數": 14,
      "無效票數": 4,
      "投票數": 18,
      "已領未投票數": 0,
      "發出票數": 18,
      "用餘票數": 8,
      "選舉人數": 26,
      "投票率": 69.2300033569336,
      "曾智勇": 0,
      "高金素梅": 2,
      "邱文生": 1,
      "孔文吉": 6,
      "瓦歷斯‧貝林 Walis‧Perin": 0,
      "簡東明 Uliw．Qaljupayare": 5
    },
    {
      "區別": "臺東市",
      "里別": "豐田里",
      "投票所": 62,
      "有效票數": 10,
      "無效票數": 0,
      "投票數": 10,
      "已領未投票數": 0,
      "發出票數": 10,
      "用餘票數": 2,
      "選舉人數": 12,
      "投票率": 83.33000183105469,
      "曾智勇": 0,
      "高金素梅": 3,
      "邱文生": 0,
      "孔文吉": 5,
      "瓦歷斯‧貝林 Walis‧Perin": 2,
      "簡東明 Uliw．Qaljupayare": 0
    },
    {
      "區別": "臺東市",
      "里別": "新園里",
      "投票所": 63,
      "有效票數": 20,
      "無效票數": 3,
      "投票數": 23,
      "已領未投票數": 0,
      "發出票數": 23,
      "用餘票數": 24,
      "選舉人數": 47,
      "投票率": 48.939998626708984,
      "曾智勇": 1,
      "高金素梅": 8,
      "邱文生": 0,
      "孔文吉": 3,
      "瓦歷斯‧貝林 Walis‧Perin": 1,
      "簡東明 Uliw．Qaljupayare": 7
    },
    {
      "區別": "臺東市",
      "里別": "建和里",
      "投票所": 64,
      "有效票數": 10,
      "無效票數": 0,
      "投票數": 10,
      "已領未投票數": 0,
      "發出票數": 10,
      "用餘票數": 7,
      "選舉人數": 17,
      "投票率": 58.81999969482422,
      "曾智勇": 1,
      "高金素梅": 6,
      "邱文生": 0,
      "孔文吉": 0,
      "瓦歷斯‧貝林 Walis‧Perin": 0,
      "簡東明 Uliw．Qaljupayare": 3
    },
    {
      "區別": "臺東市",
      "里別": "建興里",
      "投票所": 65,
      "有效票數": 2,
      "無效票數": 0,
      "投票數": 2,
      "已領未投票數": 0,
      "發出票數": 2,
      "用餘票數": 0,
      "選舉人數": 2,
      "投票率": 100,
      "曾智勇": 0,
      "高金素梅": 0,
      "邱文生": 0,
      "孔文吉": 0,
      "瓦歷斯‧貝林 Walis‧Perin": 1,
      "簡東明 Uliw．Qaljupayare": 1
    },
    {
      "區別": "臺東市",
      "里別": "建業里",
      "投票所": 66,
      "有效票數": 4,
      "無效票數": 0,
      "投票數": 4,
      "已領未投票數": 0,
      "發出票數": 4,
      "用餘票數": 5,
      "選舉人數": 9,
      "投票率": 44.439998626708984,
      "曾智勇": 0,
      "高金素梅": 2,
      "邱文生": 0,
      "孔文吉": 0,
      "瓦歷斯‧貝林 Walis‧Perin": 1,
      "簡東明 Uliw．Qaljupayare": 1
    },
    {
      "區別": "臺東市",
      "里別": "知本里",
      "投票所": 67,
      "有效票數": 10,
      "無效票數": 0,
      "投票數": 10,
      "已領未投票數": 0,
      "發出票數": 10,
      "用餘票數": 3,
      "選舉人數": 13,
      "投票率": 76.91999816894531,
      "曾智勇": 0,
      "高金素梅": 3,
      "邱文生": 0,
      "孔文吉": 3,
      "瓦歷斯‧貝林 Walis‧Perin": 2,
      "簡東明 Uliw．Qaljupayare": 2
    },
    {
      "區別": "臺東市",
      "里別": "建農里",
      "投票所": 68,
      "有效票數": 46,
      "無效票數": 6,
      "投票數": 52,
      "已領未投票數": 0,
      "發出票數": 52,
      "用餘票數": 12,
      "選舉人數": 64,
      "投票率": 81.25,
      "曾智勇": 2,
      "高金素梅": 14,
      "邱文生": 1,
      "孔文吉": 13,
      "瓦歷斯‧貝林 Walis‧Perin": 3,
      "簡東明 Uliw．Qaljupayare": 13
    },
    {
      "區別": "臺東市",
      "里別": "建農里",
      "投票所": 69,
      "有效票數": 16,
      "無效票數": 1,
      "投票數": 17,
      "已領未投票數": 0,
      "發出票數": 17,
      "用餘票數": 10,
      "選舉人數": 27,
      "投票率": 62.959999084472656,
      "曾智勇": 0,
      "高金素梅": 4,
      "邱文生": 0,
      "孔文吉": 5,
      "瓦歷斯‧貝林 Walis‧Perin": 2,
      "簡東明 Uliw．Qaljupayare": 5
    },
    {
      "區別": "成功鎮",
      "里別": "信義里",
      "投票所": 70,
      "有效票數": 1,
      "無效票數": 0,
      "投票數": 1,
      "已領未投票數": 0,
      "發出票數": 1,
      "用餘票數": 1,
      "選舉人數": 2,
      "投票率": 50,
      "曾智勇": 0,
      "高金素梅": 1,
      "邱文生": 0,
      "孔文吉": 0,
      "瓦歷斯‧貝林 Walis‧Perin": 0,
      "簡東明 Uliw．Qaljupayare": 0
    },
    {
      "區別": "成功鎮",
      "里別": "信義里",
      "投票所": 71,
      "有效票數": 1,
      "無效票數": 0,
      "投票數": 1,
      "已領未投票數": 0,
      "發出票數": 1,
      "用餘票數": 4,
      "選舉人數": 5,
      "投票率": 20,
      "曾智勇": 0,
      "高金素梅": 0,
      "邱文生": 0,
      "孔文吉": 0,
      "瓦歷斯‧貝林 Walis‧Perin": 0,
      "簡東明 Uliw．Qaljupayare": 1
    },
    {
      "區別": "成功鎮",
      "里別": "信義里",
      "投票所": 72,
      "有效票數": 0,
      "無效票數": 0,
      "投票數": 0,
      "已領未投票數": 0,
      "發出票數": 0,
      "用餘票數": 0,
      "選舉人數": 0,
      "投票率": 0,
      "曾智勇": 0,
      "高金素梅": 0,
      "邱文生": 0,
      "孔文吉": 0,
      "瓦歷斯‧貝林 Walis‧Perin": 0,
      "簡東明 Uliw．Qaljupayare": 0
    },
    {
      "區別": "成功鎮",
      "里別": "和平里",
      "投票所": 73,
      "有效票數": 2,
      "無效票數": 0,
      "投票數": 2,
      "已領未投票數": 0,
      "發出票數": 2,
      "用餘票數": 3,
      "選舉人數": 5,
      "投票率": 40,
      "曾智勇": 0,
      "高金素梅": 0,
      "邱文生": 0,
      "孔文吉": 1,
      "瓦歷斯‧貝林 Walis‧Perin": 0,
      "簡東明 Uliw．Qaljupayare": 1
    },
    {
      "區別": "成功鎮",
      "里別": "忠仁里",
      "投票所": 74,
      "有效票數": 0,
      "無效票數": 0,
      "投票數": 0,
      "已領未投票數": 0,
      "發出票數": 0,
      "用餘票數": 3,
      "選舉人數": 3,
      "投票率": 0,
      "曾智勇": 0,
      "高金素梅": 0,
      "邱文生": 0,
      "孔文吉": 0,
      "瓦歷斯‧貝林 Walis‧Perin": 0,
      "簡東明 Uliw．Qaljupayare": 0
    },
    {
      "區別": "成功鎮",
      "里別": "忠仁里",
      "投票所": 75,
      "有效票數": 3,
      "無效票數": 0,
      "投票數": 3,
      "已領未投票數": 0,
      "發出票數": 3,
      "用餘票數": 0,
      "選舉人數": 3,
      "投票率": 100,
      "曾智勇": 0,
      "高金素梅": 1,
      "邱文生": 0,
      "孔文吉": 1,
      "瓦歷斯‧貝林 Walis‧Perin": 0,
      "簡東明 Uliw．Qaljupayare": 1
    },
    {
      "區別": "成功鎮",
      "里別": "忠仁里",
      "投票所": 76,
      "有效票數": 0,
      "無效票數": 0,
      "投票數": 0,
      "已領未投票數": 0,
      "發出票數": 0,
      "用餘票數": 0,
      "選舉人數": 0,
      "投票率": 0,
      "曾智勇": 0,
      "高金素梅": 0,
      "邱文生": 0,
      "孔文吉": 0,
      "瓦歷斯‧貝林 Walis‧Perin": 0,
      "簡東明 Uliw．Qaljupayare": 0
    },
    {
      "區別": "成功鎮",
      "里別": "忠智里",
      "投票所": 77,
      "有效票數": 0,
      "無效票數": 0,
      "投票數": 0,
      "已領未投票數": 0,
      "發出票數": 0,
      "用餘票數": 0,
      "選舉人數": 0,
      "投票率": 0,
      "曾智勇": 0,
      "高金素梅": 0,
      "邱文生": 0,
      "孔文吉": 0,
      "瓦歷斯‧貝林 Walis‧Perin": 0,
      "簡東明 Uliw．Qaljupayare": 0
    },
    {
      "區別": "成功鎮",
      "里別": "忠智里",
      "投票所": 78,
      "有效票數": 4,
      "無效票數": 0,
      "投票數": 4,
      "已領未投票數": 0,
      "發出票數": 4,
      "用餘票數": 3,
      "選舉人數": 7,
      "投票率": 57.13999938964844,
      "曾智勇": 0,
      "高金素梅": 3,
      "邱文生": 1,
      "孔文吉": 0,
      "瓦歷斯‧貝林 Walis‧Perin": 0,
      "簡東明 Uliw．Qaljupayare": 0
    },
    {
      "區別": "成功鎮",
      "里別": "三民里",
      "投票所": 79,
      "有效票數": 3,
      "無效票數": 0,
      "投票數": 3,
      "已領未投票數": 0,
      "發出票數": 3,
      "用餘票數": 6,
      "選舉人數": 9,
      "投票率": 33.33000183105469,
      "曾智勇": 0,
      "高金素梅": 0,
      "邱文生": 1,
      "孔文吉": 1,
      "瓦歷斯‧貝林 Walis‧Perin": 1,
      "簡東明 Uliw．Qaljupayare": 0
    },
    {
      "區別": "成功鎮",
      "里別": "三民里",
      "投票所": 80,
      "有效票數": 4,
      "無效票數": 0,
      "投票數": 4,
      "已領未投票數": 0,
      "發出票數": 4,
      "用餘票數": 1,
      "選舉人數": 5,
      "投票率": 80,
      "曾智勇": 1,
      "高金素梅": 3,
      "邱文生": 0,
      "孔文吉": 0,
      "瓦歷斯‧貝林 Walis‧Perin": 0,
      "簡東明 Uliw．Qaljupayare": 0
    },
    {
      "區別": "成功鎮",
      "里別": "三仙里",
      "投票所": 81,
      "有效票數": 1,
      "無效票數": 0,
      "投票數": 1,
      "已領未投票數": 0,
      "發出票數": 1,
      "用餘票數": 0,
      "選舉人數": 1,
      "投票率": 100,
      "曾智勇": 0,
      "高金素梅": 1,
      "邱文生": 0,
      "孔文吉": 0,
      "瓦歷斯‧貝林 Walis‧Perin": 0,
      "簡東明 Uliw．Qaljupayare": 0
    },
    {
      "區別": "成功鎮",
      "里別": "三仙里",
      "投票所": 82,
      "有效票數": 3,
      "無效票數": 0,
      "投票數": 3,
      "已領未投票數": 0,
      "發出票數": 3,
      "用餘票數": 1,
      "選舉人數": 4,
      "投票率": 75,
      "曾智勇": 0,
      "高金素梅": 0,
      "邱文生": 0,
      "孔文吉": 2,
      "瓦歷斯‧貝林 Walis‧Perin": 1,
      "簡東明 Uliw．Qaljupayare": 0
    },
    {
      "區別": "成功鎮",
      "里別": "忠孝里",
      "投票所": 83,
      "有效票數": 0,
      "無效票數": 1,
      "投票數": 1,
      "已領未投票數": 0,
      "發出票數": 1,
      "用餘票數": 0,
      "選舉人數": 1,
      "投票率": 100,
      "曾智勇": 0,
      "高金素梅": 0,
      "邱文生": 0,
      "孔文吉": 0,
      "瓦歷斯‧貝林 Walis‧Perin": 0,
      "簡東明 Uliw．Qaljupayare": 0
    },
    {
      "區別": "成功鎮",
      "里別": "忠孝里",
      "投票所": 84,
      "有效票數": 1,
      "無效票數": 0,
      "投票數": 1,
      "已領未投票數": 0,
      "發出票數": 1,
      "用餘票數": 5,
      "選舉人數": 6,
      "投票率": 16.670000076293945,
      "曾智勇": 0,
      "高金素梅": 1,
      "邱文生": 0,
      "孔文吉": 0,
      "瓦歷斯‧貝林 Walis‧Perin": 0,
      "簡東明 Uliw．Qaljupayare": 0
    },
    {
      "區別": "成功鎮",
      "里別": "博愛里",
      "投票所": 85,
      "有效票數": 2,
      "無效票數": 0,
      "投票數": 2,
      "已領未投票數": 0,
      "發出票數": 2,
      "用餘票數": 2,
      "選舉人數": 4,
      "投票率": 50,
      "曾智勇": 0,
      "高金素梅": 0,
      "邱文生": 0,
      "孔文吉": 1,
      "瓦歷斯‧貝林 Walis‧Perin": 0,
      "簡東明 Uliw．Qaljupayare": 1
    },
    {
      "區別": "關山鎮",
      "里別": "里里",
      "投票所": 86,
      "有效票數": 14,
      "無效票數": 0,
      "投票數": 14,
      "已領未投票數": 0,
      "發出票數": 14,
      "用餘票數": 6,
      "選舉人數": 20,
      "投票率": 70,
      "曾智勇": 0,
      "高金素梅": 2,
      "邱文生": 0,
      "孔文吉": 8,
      "瓦歷斯‧貝林 Walis‧Perin": 2,
      "簡東明 Uliw．Qaljupayare": 2
    },
    {
      "區別": "關山鎮",
      "里別": "里里",
      "投票所": 87,
      "有效票數": 22,
      "無效票數": 0,
      "投票數": 22,
      "已領未投票數": 0,
      "發出票數": 22,
      "用餘票數": 9,
      "選舉人數": 31,
      "投票率": 70.97000122070312,
      "曾智勇": 2,
      "高金素梅": 3,
      "邱文生": 0,
      "孔文吉": 11,
      "瓦歷斯‧貝林 Walis‧Perin": 2,
      "簡東明 Uliw．Qaljupayare": 4
    },
    {
      "區別": "關山鎮",
      "里別": "中福里",
      "投票所": 88,
      "有效票數": 11,
      "無效票數": 0,
      "投票數": 11,
      "已領未投票數": 0,
      "發出票數": 11,
      "用餘票數": 3,
      "選舉人數": 14,
      "投票率": 78.56999969482422,
      "曾智勇": 0,
      "高金素梅": 1,
      "邱文生": 0,
      "孔文吉": 8,
      "瓦歷斯‧貝林 Walis‧Perin": 0,
      "簡東明 Uliw．Qaljupayare": 2
    },
    {
      "區別": "關山鎮",
      "里別": "新福里",
      "投票所": 89,
      "有效票數": 5,
      "無效票數": 0,
      "投票數": 5,
      "已領未投票數": 0,
      "發出票數": 5,
      "用餘票數": 4,
      "選舉人數": 9,
      "投票率": 55.560001373291016,
      "曾智勇": 0,
      "高金素梅": 4,
      "邱文生": 0,
      "孔文吉": 1,
      "瓦歷斯‧貝林 Walis‧Perin": 0,
      "簡東明 Uliw．Qaljupayare": 0
    },
    {
      "區別": "關山鎮",
      "里別": "豐泉里",
      "投票所": 90,
      "有效票數": 30,
      "無效票數": 0,
      "投票數": 30,
      "已領未投票數": 0,
      "發出票數": 30,
      "用餘票數": 17,
      "選舉人數": 47,
      "投票率": 63.83000183105469,
      "曾智勇": 1,
      "高金素梅": 4,
      "邱文生": 1,
      "孔文吉": 10,
      "瓦歷斯‧貝林 Walis‧Perin": 6,
      "簡東明 Uliw．Qaljupayare": 8
    },
    {
      "區別": "關山鎮",
      "里別": "月眉里",
      "投票所": 91,
      "有效票數": 10,
      "無效票數": 1,
      "投票數": 11,
      "已領未投票數": 0,
      "發出票數": 11,
      "用餘票數": 6,
      "選舉人數": 17,
      "投票率": 64.70999908447266,
      "曾智勇": 0,
      "高金素梅": 0,
      "邱文生": 0,
      "孔文吉": 6,
      "瓦歷斯‧貝林 Walis‧Perin": 0,
      "簡東明 Uliw．Qaljupayare": 4
    },
    {
      "區別": "關山鎮",
      "里別": "德高里",
      "投票所": 92,
      "有效票數": 3,
      "無效票數": 0,
      "投票數": 3,
      "已領未投票數": 0,
      "發出票數": 3,
      "用餘票數": 1,
      "選舉人數": 4,
      "投票率": 75,
      "曾智勇": 0,
      "高金素梅": 1,
      "邱文生": 0,
      "孔文吉": 1,
      "瓦歷斯‧貝林 Walis‧Perin": 0,
      "簡東明 Uliw．Qaljupayare": 1
    },
    {
      "區別": "關山鎮",
      "里別": "德高里",
      "投票所": 93,
      "有效票數": 9,
      "無效票數": 3,
      "投票數": 12,
      "已領未投票數": 0,
      "發出票數": 12,
      "用餘票數": 7,
      "選舉人數": 19,
      "投票率": 63.15999984741211,
      "曾智勇": 1,
      "高金素梅": 0,
      "邱文生": 0,
      "孔文吉": 3,
      "瓦歷斯‧貝林 Walis‧Perin": 1,
      "簡東明 Uliw．Qaljupayare": 4
    },
    {
      "區別": "關山鎮",
      "里別": "電光里",
      "投票所": 94,
      "有效票數": 3,
      "無效票數": 0,
      "投票數": 3,
      "已領未投票數": 0,
      "發出票數": 3,
      "用餘票數": 3,
      "選舉人數": 6,
      "投票率": 50,
      "曾智勇": 0,
      "高金素梅": 2,
      "邱文生": 0,
      "孔文吉": 1,
      "瓦歷斯‧貝林 Walis‧Perin": 0,
      "簡東明 Uliw．Qaljupayare": 0
    },
    {
      "區別": "卑南鄉",
      "里別": "賓朗村",
      "投票所": 95,
      "有效票數": 2,
      "無效票數": 0,
      "投票數": 2,
      "已領未投票數": 0,
      "發出票數": 2,
      "用餘票數": 2,
      "選舉人數": 4,
      "投票率": 50,
      "曾智勇": 0,
      "高金素梅": 0,
      "邱文生": 0,
      "孔文吉": 0,
      "瓦歷斯‧貝林 Walis‧Perin": 0,
      "簡東明 Uliw．Qaljupayare": 2
    },
    {
      "區別": "卑南鄉",
      "里別": "賓朗村",
      "投票所": 96,
      "有效票數": 18,
      "無效票數": 0,
      "投票數": 18,
      "已領未投票數": 0,
      "發出票數": 18,
      "用餘票數": 13,
      "選舉人數": 31,
      "投票率": 58.060001373291016,
      "曾智勇": 1,
      "高金素梅": 1,
      "邱文生": 0,
      "孔文吉": 5,
      "瓦歷斯‧貝林 Walis‧Perin": 2,
      "簡東明 Uliw．Qaljupayare": 9
    },
    {
      "區別": "卑南鄉",
      "里別": "美農村",
      "投票所": 97,
      "有效票數": 0,
      "無效票數": 0,
      "投票數": 0,
      "已領未投票數": 0,
      "發出票數": 0,
      "用餘票數": 0,
      "選舉人數": 0,
      "投票率": 0,
      "曾智勇": 0,
      "高金素梅": 0,
      "邱文生": 0,
      "孔文吉": 0,
      "瓦歷斯‧貝林 Walis‧Perin": 0,
      "簡東明 Uliw．Qaljupayare": 0
    },
    {
      "區別": "卑南鄉",
      "里別": "美農村",
      "投票所": 98,
      "有效票數": 1,
      "無效票數": 0,
      "投票數": 1,
      "已領未投票數": 0,
      "發出票數": 1,
      "用餘票數": 3,
      "選舉人數": 4,
      "投票率": 25,
      "曾智勇": 0,
      "高金素梅": 0,
      "邱文生": 0,
      "孔文吉": 0,
      "瓦歷斯‧貝林 Walis‧Perin": 0,
      "簡東明 Uliw．Qaljupayare": 1
    },
    {
      "區別": "卑南鄉",
      "里別": "美農村",
      "投票所": 99,
      "有效票數": 3,
      "無效票數": 0,
      "投票數": 3,
      "已領未投票數": 0,
      "發出票數": 3,
      "用餘票數": 0,
      "選舉人數": 3,
      "投票率": 100,
      "曾智勇": 0,
      "高金素梅": 0,
      "邱文生": 0,
      "孔文吉": 3,
      "瓦歷斯‧貝林 Walis‧Perin": 0,
      "簡東明 Uliw．Qaljupayare": 0
    },
    {
      "區別": "卑南鄉",
      "里別": "初鹿村",
      "投票所": 100,
      "有效票數": 10,
      "無效票數": 1,
      "投票數": 11,
      "已領未投票數": 0,
      "發出票數": 11,
      "用餘票數": 7,
      "選舉人數": 18,
      "投票率": 61.11000061035156,
      "曾智勇": 1,
      "高金素梅": 5,
      "邱文生": 0,
      "孔文吉": 3,
      "瓦歷斯‧貝林 Walis‧Perin": 1,
      "簡東明 Uliw．Qaljupayare": 0
    },
    {
      "區別": "卑南鄉",
      "里別": "初鹿村",
      "投票所": 101,
      "有效票數": 3,
      "無效票數": 0,
      "投票數": 3,
      "已領未投票數": 0,
      "發出票數": 3,
      "用餘票數": 0,
      "選舉人數": 3,
      "投票率": 100,
      "曾智勇": 0,
      "高金素梅": 1,
      "邱文生": 0,
      "孔文吉": 2,
      "瓦歷斯‧貝林 Walis‧Perin": 0,
      "簡東明 Uliw．Qaljupayare": 0
    },
    {
      "區別": "卑南鄉",
      "里別": "明峰村",
      "投票所": 102,
      "有效票數": 1,
      "無效票數": 0,
      "投票數": 1,
      "已領未投票數": 0,
      "發出票數": 1,
      "用餘票數": 0,
      "選舉人數": 1,
      "投票率": 100,
      "曾智勇": 0,
      "高金素梅": 0,
      "邱文生": 0,
      "孔文吉": 1,
      "瓦歷斯‧貝林 Walis‧Perin": 0,
      "簡東明 Uliw．Qaljupayare": 0
    },
    {
      "區別": "卑南鄉",
      "里別": "明峰村",
      "投票所": 103,
      "有效票數": 6,
      "無效票數": 0,
      "投票數": 6,
      "已領未投票數": 0,
      "發出票數": 6,
      "用餘票數": 6,
      "選舉人數": 12,
      "投票率": 50,
      "曾智勇": 0,
      "高金素梅": 1,
      "邱文生": 0,
      "孔文吉": 3,
      "瓦歷斯‧貝林 Walis‧Perin": 0,
      "簡東明 Uliw．Qaljupayare": 2
    },
    {
      "區別": "卑南鄉",
      "里別": "嘉豐村",
      "投票所": 104,
      "有效票數": 1,
      "無效票數": 0,
      "投票數": 1,
      "已領未投票數": 0,
      "發出票數": 1,
      "用餘票數": 4,
      "選舉人數": 5,
      "投票率": 20,
      "曾智勇": 0,
      "高金素梅": 1,
      "邱文生": 0,
      "孔文吉": 0,
      "瓦歷斯‧貝林 Walis‧Perin": 0,
      "簡東明 Uliw．Qaljupayare": 0
    },
    {
      "區別": "卑南鄉",
      "里別": "嘉豐村",
      "投票所": 105,
      "有效票數": 2,
      "無效票數": 0,
      "投票數": 2,
      "已領未投票數": 0,
      "發出票數": 2,
      "用餘票數": 1,
      "選舉人數": 3,
      "投票率": 66.66999816894531,
      "曾智勇": 0,
      "高金素梅": 1,
      "邱文生": 0,
      "孔文吉": 0,
      "瓦歷斯‧貝林 Walis‧Perin": 0,
      "簡東明 Uliw．Qaljupayare": 1
    },
    {
      "區別": "卑南鄉",
      "里別": "太平村",
      "投票所": 106,
      "有效票數": 20,
      "無效票數": 3,
      "投票數": 23,
      "已領未投票數": 0,
      "發出票數": 23,
      "用餘票數": 19,
      "選舉人數": 42,
      "投票率": 54.7599983215332,
      "曾智勇": 5,
      "高金素梅": 5,
      "邱文生": 0,
      "孔文吉": 4,
      "瓦歷斯‧貝林 Walis‧Perin": 2,
      "簡東明 Uliw．Qaljupayare": 4
    },
    {
      "區別": "卑南鄉",
      "里別": "太平村",
      "投票所": 107,
      "有效票數": 17,
      "無效票數": 0,
      "投票數": 17,
      "已領未投票數": 0,
      "發出票數": 17,
      "用餘票數": 1,
      "選舉人數": 18,
      "投票率": 94.44000244140625,
      "曾智勇": 3,
      "高金素梅": 3,
      "邱文生": 0,
      "孔文吉": 1,
      "瓦歷斯‧貝林 Walis‧Perin": 0,
      "簡東明 Uliw．Qaljupayare": 10
    },
    {
      "區別": "卑南鄉",
      "里別": "太平村",
      "投票所": 108,
      "有效票數": 35,
      "無效票數": 2,
      "投票數": 37,
      "已領未投票數": 0,
      "發出票數": 37,
      "用餘票數": 25,
      "選舉人數": 62,
      "投票率": 59.68000030517578,
      "曾智勇": 0,
      "高金素梅": 14,
      "邱文生": 0,
      "孔文吉": 9,
      "瓦歷斯‧貝林 Walis‧Perin": 8,
      "簡東明 Uliw．Qaljupayare": 4
    },
    {
      "區別": "卑南鄉",
      "里別": "泰安村",
      "投票所": 109,
      "有效票數": 19,
      "無效票數": 1,
      "投票數": 20,
      "已領未投票數": 0,
      "發出票數": 20,
      "用餘票數": 21,
      "選舉人數": 41,
      "投票率": 48.779998779296875,
      "曾智勇": 1,
      "高金素梅": 4,
      "邱文生": 1,
      "孔文吉": 7,
      "瓦歷斯‧貝林 Walis‧Perin": 1,
      "簡東明 Uliw．Qaljupayare": 5
    },
    {
      "區別": "卑南鄉",
      "里別": "利嘉村",
      "投票所": 110,
      "有效票數": 12,
      "無效票數": 0,
      "投票數": 12,
      "已領未投票數": 0,
      "發出票數": 12,
      "用餘票數": 1,
      "選舉人數": 13,
      "投票率": 92.30999755859375,
      "曾智勇": 0,
      "高金素梅": 2,
      "邱文生": 0,
      "孔文吉": 3,
      "瓦歷斯‧貝林 Walis‧Perin": 3,
      "簡東明 Uliw．Qaljupayare": 4
    },
    {
      "區別": "卑南鄉",
      "里別": "東興村",
      "投票所": 111,
      "有效票數": 49,
      "無效票數": 0,
      "投票數": 49,
      "已領未投票數": 0,
      "發出票數": 49,
      "用餘票數": 25,
      "選舉人數": 74,
      "投票率": 66.22000122070312,
      "曾智勇": 5,
      "高金素梅": 11,
      "邱文生": 0,
      "孔文吉": 9,
      "瓦歷斯‧貝林 Walis‧Perin": 5,
      "簡東明 Uliw．Qaljupayare": 19
    },
    {
      "區別": "卑南鄉",
      "里別": "溫泉村",
      "投票所": 112,
      "有效票數": 7,
      "無效票數": 1,
      "投票數": 8,
      "已領未投票數": 0,
      "發出票數": 8,
      "用餘票數": 3,
      "選舉人數": 11,
      "投票率": 72.7300033569336,
      "曾智勇": 1,
      "高金素梅": 3,
      "邱文生": 0,
      "孔文吉": 1,
      "瓦歷斯‧貝林 Walis‧Perin": 2,
      "簡東明 Uliw．Qaljupayare": 0
    },
    {
      "區別": "卑南鄉",
      "里別": "溫泉村",
      "投票所": 113,
      "有效票數": 0,
      "無效票數": 0,
      "投票數": 0,
      "已領未投票數": 0,
      "發出票數": 0,
      "用餘票數": 0,
      "選舉人數": 0,
      "投票率": 0,
      "曾智勇": 0,
      "高金素梅": 0,
      "邱文生": 0,
      "孔文吉": 0,
      "瓦歷斯‧貝林 Walis‧Perin": 0,
      "簡東明 Uliw．Qaljupayare": 0
    },
    {
      "區別": "卑南鄉",
      "里別": "富山村",
      "投票所": 114,
      "有效票數": 3,
      "無效票數": 1,
      "投票數": 4,
      "已領未投票數": 0,
      "發出票數": 4,
      "用餘票數": 0,
      "選舉人數": 4,
      "投票率": 100,
      "曾智勇": 0,
      "高金素梅": 0,
      "邱文生": 0,
      "孔文吉": 2,
      "瓦歷斯‧貝林 Walis‧Perin": 0,
      "簡東明 Uliw．Qaljupayare": 1
    },
    {
      "區別": "卑南鄉",
      "里別": "富源村",
      "投票所": 115,
      "有效票數": 1,
      "無效票數": 0,
      "投票數": 1,
      "已領未投票數": 0,
      "發出票數": 1,
      "用餘票數": 0,
      "選舉人數": 1,
      "投票率": 100,
      "曾智勇": 0,
      "高金素梅": 0,
      "邱文生": 1,
      "孔文吉": 0,
      "瓦歷斯‧貝林 Walis‧Perin": 0,
      "簡東明 Uliw．Qaljupayare": 0
    },
    {
      "區別": "卑南鄉",
      "里別": "利吉村",
      "投票所": 116,
      "有效票數": 0,
      "無效票數": 0,
      "投票數": 0,
      "已領未投票數": 0,
      "發出票數": 0,
      "用餘票數": 0,
      "選舉人數": 0,
      "投票率": 0,
      "曾智勇": 0,
      "高金素梅": 0,
      "邱文生": 0,
      "孔文吉": 0,
      "瓦歷斯‧貝林 Walis‧Perin": 0,
      "簡東明 Uliw．Qaljupayare": 0
    },
    {
      "區別": "鹿野鄉",
      "里別": "鹿野村",
      "投票所": 117,
      "有效票數": 4,
      "無效票數": 0,
      "投票數": 4,
      "已領未投票數": 0,
      "發出票數": 4,
      "用餘票數": 4,
      "選舉人數": 8,
      "投票率": 50,
      "曾智勇": 0,
      "高金素梅": 0,
      "邱文生": 0,
      "孔文吉": 2,
      "瓦歷斯‧貝林 Walis‧Perin": 0,
      "簡東明 Uliw．Qaljupayare": 2
    },
    {
      "區別": "鹿野鄉",
      "里別": "鹿野村",
      "投票所": 118,
      "有效票數": 5,
      "無效票數": 0,
      "投票數": 5,
      "已領未投票數": 0,
      "發出票數": 5,
      "用餘票數": 3,
      "選舉人數": 8,
      "投票率": 62.5,
      "曾智勇": 0,
      "高金素梅": 1,
      "邱文生": 0,
      "孔文吉": 3,
      "瓦歷斯‧貝林 Walis‧Perin": 0,
      "簡東明 Uliw．Qaljupayare": 1
    },
    {
      "區別": "鹿野鄉",
      "里別": "龍田村",
      "投票所": 119,
      "有效票數": 4,
      "無效票數": 0,
      "投票數": 4,
      "已領未投票數": 0,
      "發出票數": 4,
      "用餘票數": 5,
      "選舉人數": 9,
      "投票率": 44.439998626708984,
      "曾智勇": 0,
      "高金素梅": 1,
      "邱文生": 0,
      "孔文吉": 3,
      "瓦歷斯‧貝林 Walis‧Perin": 0,
      "簡東明 Uliw．Qaljupayare": 0
    },
    {
      "區別": "鹿野鄉",
      "里別": "永安村",
      "投票所": 120,
      "有效票數": 2,
      "無效票數": 1,
      "投票數": 3,
      "已領未投票數": 0,
      "發出票數": 3,
      "用餘票數": 2,
      "選舉人數": 5,
      "投票率": 60,
      "曾智勇": 1,
      "高金素梅": 0,
      "邱文生": 1,
      "孔文吉": 0,
      "瓦歷斯‧貝林 Walis‧Perin": 0,
      "簡東明 Uliw．Qaljupayare": 0
    },
    {
      "區別": "鹿野鄉",
      "里別": "永安村",
      "投票所": 121,
      "有效票數": 13,
      "無效票數": 0,
      "投票數": 13,
      "已領未投票數": 0,
      "發出票數": 13,
      "用餘票數": 9,
      "選舉人數": 22,
      "投票率": 59.09000015258789,
      "曾智勇": 1,
      "高金素梅": 1,
      "邱文生": 1,
      "孔文吉": 10,
      "瓦歷斯‧貝林 Walis‧Perin": 0,
      "簡東明 Uliw．Qaljupayare": 0
    },
    {
      "區別": "鹿野鄉",
      "里別": "瑞隆村",
      "投票所": 122,
      "有效票數": 10,
      "無效票數": 1,
      "投票數": 11,
      "已領未投票數": 0,
      "發出票數": 11,
      "用餘票數": 7,
      "選舉人數": 18,
      "投票率": 61.11000061035156,
      "曾智勇": 1,
      "高金素梅": 4,
      "邱文生": 0,
      "孔文吉": 4,
      "瓦歷斯‧貝林 Walis‧Perin": 1,
      "簡東明 Uliw．Qaljupayare": 0
    },
    {
      "區別": "鹿野鄉",
      "里別": "瑞源村",
      "投票所": 123,
      "有效票數": 7,
      "無效票數": 1,
      "投票數": 8,
      "已領未投票數": 0,
      "發出票數": 8,
      "用餘票數": 5,
      "選舉人數": 13,
      "投票率": 61.540000915527344,
      "曾智勇": 1,
      "高金素梅": 2,
      "邱文生": 0,
      "孔文吉": 3,
      "瓦歷斯‧貝林 Walis‧Perin": 0,
      "簡東明 Uliw．Qaljupayare": 1
    },
    {
      "區別": "鹿野鄉",
      "里別": "瑞和村",
      "投票所": 124,
      "有效票數": 0,
      "無效票數": 0,
      "投票數": 0,
      "已領未投票數": 0,
      "發出票數": 0,
      "用餘票數": 3,
      "選舉人數": 3,
      "投票率": 0,
      "曾智勇": 0,
      "高金素梅": 0,
      "邱文生": 0,
      "孔文吉": 0,
      "瓦歷斯‧貝林 Walis‧Perin": 0,
      "簡東明 Uliw．Qaljupayare": 0
    },
    {
      "區別": "鹿野鄉",
      "里別": "瑞豐村",
      "投票所": 125,
      "有效票數": 11,
      "無效票數": 0,
      "投票數": 11,
      "已領未投票數": 0,
      "發出票數": 11,
      "用餘票數": 7,
      "選舉人數": 18,
      "投票率": 61.11000061035156,
      "曾智勇": 0,
      "高金素梅": 2,
      "邱文生": 0,
      "孔文吉": 5,
      "瓦歷斯‧貝林 Walis‧Perin": 1,
      "簡東明 Uliw．Qaljupayare": 3
    },
    {
      "區別": "鹿野鄉",
      "里別": "瑞豐村",
      "投票所": 126,
      "有效票數": 9,
      "無效票數": 0,
      "投票數": 9,
      "已領未投票數": 0,
      "發出票數": 9,
      "用餘票數": 4,
      "選舉人數": 13,
      "投票率": 69.2300033569336,
      "曾智勇": 3,
      "高金素梅": 0,
      "邱文生": 0,
      "孔文吉": 0,
      "瓦歷斯‧貝林 Walis‧Perin": 1,
      "簡東明 Uliw．Qaljupayare": 5
    },
    {
      "區別": "池上鄉",
      "里別": "福原村",
      "投票所": 127,
      "有效票數": 13,
      "無效票數": 0,
      "投票數": 13,
      "已領未投票數": 0,
      "發出票數": 13,
      "用餘票數": 10,
      "選舉人數": 23,
      "投票率": 56.52000045776367,
      "曾智勇": 1,
      "高金素梅": 2,
      "邱文生": 0,
      "孔文吉": 8,
      "瓦歷斯‧貝林 Walis‧Perin": 0,
      "簡東明 Uliw．Qaljupayare": 2
    },
    {
      "區別": "池上鄉",
      "里別": "福原村",
      "投票所": 128,
      "有效票數": 6,
      "無效票數": 0,
      "投票數": 6,
      "已領未投票數": 0,
      "發出票數": 6,
      "用餘票數": 2,
      "選舉人數": 8,
      "投票率": 75,
      "曾智勇": 1,
      "高金素梅": 1,
      "邱文生": 0,
      "孔文吉": 3,
      "瓦歷斯‧貝林 Walis‧Perin": 0,
      "簡東明 Uliw．Qaljupayare": 1
    },
    {
      "區別": "池上鄉",
      "里別": "福文村",
      "投票所": 129,
      "有效票數": 5,
      "無效票數": 0,
      "投票數": 5,
      "已領未投票數": 0,
      "發出票數": 5,
      "用餘票數": 0,
      "選舉人數": 5,
      "投票率": 100,
      "曾智勇": 0,
      "高金素梅": 1,
      "邱文生": 0,
      "孔文吉": 2,
      "瓦歷斯‧貝林 Walis‧Perin": 0,
      "簡東明 Uliw．Qaljupayare": 2
    },
    {
      "區別": "池上鄉",
      "里別": "福文村",
      "投票所": 130,
      "有效票數": 10,
      "無效票數": 1,
      "投票數": 11,
      "已領未投票數": 0,
      "發出票數": 11,
      "用餘票數": 10,
      "選舉人數": 21,
      "投票率": 52.380001068115234,
      "曾智勇": 1,
      "高金素梅": 1,
      "邱文生": 0,
      "孔文吉": 6,
      "瓦歷斯‧貝林 Walis‧Perin": 0,
      "簡東明 Uliw．Qaljupayare": 2
    },
    {
      "區別": "池上鄉",
      "里別": "慶豐村",
      "投票所": 131,
      "有效票數": 4,
      "無效票數": 0,
      "投票數": 4,
      "已領未投票數": 0,
      "發出票數": 4,
      "用餘票數": 4,
      "選舉人數": 8,
      "投票率": 50,
      "曾智勇": 0,
      "高金素梅": 1,
      "邱文生": 0,
      "孔文吉": 2,
      "瓦歷斯‧貝林 Walis‧Perin": 0,
      "簡東明 Uliw．Qaljupayare": 1
    },
    {
      "區別": "池上鄉",
      "里別": "大坡村",
      "投票所": 132,
      "有效票數": 0,
      "無效票數": 0,
      "投票數": 0,
      "已領未投票數": 0,
      "發出票數": 0,
      "用餘票數": 3,
      "選舉人數": 3,
      "投票率": 0,
      "曾智勇": 0,
      "高金素梅": 0,
      "邱文生": 0,
      "孔文吉": 0,
      "瓦歷斯‧貝林 Walis‧Perin": 0,
      "簡東明 Uliw．Qaljupayare": 0
    },
    {
      "區別": "池上鄉",
      "里別": "大埔村",
      "投票所": 133,
      "有效票數": 1,
      "無效票數": 0,
      "投票數": 1,
      "已領未投票數": 0,
      "發出票數": 1,
      "用餘票數": 2,
      "選舉人數": 3,
      "投票率": 33.33000183105469,
      "曾智勇": 0,
      "高金素梅": 0,
      "邱文生": 1,
      "孔文吉": 0,
      "瓦歷斯‧貝林 Walis‧Perin": 0,
      "簡東明 Uliw．Qaljupayare": 0
    },
    {
      "區別": "池上鄉",
      "里別": "大埔村",
      "投票所": 134,
      "有效票數": 1,
      "無效票數": 0,
      "投票數": 1,
      "已領未投票數": 0,
      "發出票數": 1,
      "用餘票數": 2,
      "選舉人數": 3,
      "投票率": 33.33000183105469,
      "曾智勇": 0,
      "高金素梅": 0,
      "邱文生": 0,
      "孔文吉": 1,
      "瓦歷斯‧貝林 Walis‧Perin": 0,
      "簡東明 Uliw．Qaljupayare": 0
    },
    {
      "區別": "池上鄉",
      "里別": "新興村",
      "投票所": 135,
      "有效票數": 4,
      "無效票數": 1,
      "投票數": 5,
      "已領未投票數": 0,
      "發出票數": 5,
      "用餘票數": 8,
      "選舉人數": 13,
      "投票率": 38.459999084472656,
      "曾智勇": 0,
      "高金素梅": 0,
      "邱文生": 0,
      "孔文吉": 3,
      "瓦歷斯‧貝林 Walis‧Perin": 0,
      "簡東明 Uliw．Qaljupayare": 1
    },
    {
      "區別": "池上鄉",
      "里別": "錦園村",
      "投票所": 136,
      "有效票數": 0,
      "無效票數": 0,
      "投票數": 0,
      "已領未投票數": 0,
      "發出票數": 0,
      "用餘票數": 0,
      "選舉人數": 0,
      "投票率": 0,
      "曾智勇": 0,
      "高金素梅": 0,
      "邱文生": 0,
      "孔文吉": 0,
      "瓦歷斯‧貝林 Walis‧Perin": 0,
      "簡東明 Uliw．Qaljupayare": 0
    },
    {
      "區別": "池上鄉",
      "里別": "萬安村",
      "投票所": 137,
      "有效票數": 2,
      "無效票數": 0,
      "投票數": 2,
      "已領未投票數": 0,
      "發出票數": 2,
      "用餘票數": 0,
      "選舉人數": 2,
      "投票率": 100,
      "曾智勇": 0,
      "高金素梅": 0,
      "邱文生": 0,
      "孔文吉": 2,
      "瓦歷斯‧貝林 Walis‧Perin": 0,
      "簡東明 Uliw．Qaljupayare": 0
    },
    {
      "區別": "池上鄉",
      "里別": "富興村",
      "投票所": 138,
      "有效票數": 3,
      "無效票數": 0,
      "投票數": 3,
      "已領未投票數": 0,
      "發出票數": 3,
      "用餘票數": 1,
      "選舉人數": 4,
      "投票率": 75,
      "曾智勇": 0,
      "高金素梅": 0,
      "邱文生": 0,
      "孔文吉": 2,
      "瓦歷斯‧貝林 Walis‧Perin": 0,
      "簡東明 Uliw．Qaljupayare": 1
    },
    {
      "區別": "池上鄉",
      "里別": "振興村",
      "投票所": 139,
      "有效票數": 1,
      "無效票數": 0,
      "投票數": 1,
      "已領未投票數": 0,
      "發出票數": 1,
      "用餘票數": 2,
      "選舉人數": 3,
      "投票率": 33.33000183105469,
      "曾智勇": 0,
      "高金素梅": 0,
      "邱文生": 0,
      "孔文吉": 1,
      "瓦歷斯‧貝林 Walis‧Perin": 0,
      "簡東明 Uliw．Qaljupayare": 0
    },
    {
      "區別": "東河鄉",
      "里別": "都蘭村",
      "投票所": 140,
      "有效票數": 0,
      "無效票數": 0,
      "投票數": 0,
      "已領未投票數": 0,
      "發出票數": 0,
      "用餘票數": 0,
      "選舉人數": 0,
      "投票率": 0,
      "曾智勇": 0,
      "高金素梅": 0,
      "邱文生": 0,
      "孔文吉": 0,
      "瓦歷斯‧貝林 Walis‧Perin": 0,
      "簡東明 Uliw．Qaljupayare": 0
    },
    {
      "區別": "東河鄉",
      "里別": "都蘭村",
      "投票所": 141,
      "有效票數": 5,
      "無效票數": 0,
      "投票數": 5,
      "已領未投票數": 0,
      "發出票數": 5,
      "用餘票數": 3,
      "選舉人數": 8,
      "投票率": 62.5,
      "曾智勇": 1,
      "高金素梅": 1,
      "邱文生": 0,
      "孔文吉": 1,
      "瓦歷斯‧貝林 Walis‧Perin": 1,
      "簡東明 Uliw．Qaljupayare": 1
    },
    {
      "區別": "東河鄉",
      "里別": "都蘭村",
      "投票所": 142,
      "有效票數": 4,
      "無效票數": 0,
      "投票數": 4,
      "已領未投票數": 0,
      "發出票數": 4,
      "用餘票數": 2,
      "選舉人數": 6,
      "投票率": 66.66999816894531,
      "曾智勇": 1,
      "高金素梅": 0,
      "邱文生": 0,
      "孔文吉": 2,
      "瓦歷斯‧貝林 Walis‧Perin": 0,
      "簡東明 Uliw．Qaljupayare": 1
    },
    {
      "區別": "東河鄉",
      "里別": "興昌村",
      "投票所": 143,
      "有效票數": 5,
      "無效票數": 1,
      "投票數": 6,
      "已領未投票數": 0,
      "發出票數": 6,
      "用餘票數": 2,
      "選舉人數": 8,
      "投票率": 75,
      "曾智勇": 0,
      "高金素梅": 3,
      "邱文生": 0,
      "孔文吉": 2,
      "瓦歷斯‧貝林 Walis‧Perin": 0,
      "簡東明 Uliw．Qaljupayare": 0
    },
    {
      "區別": "東河鄉",
      "里別": "隆昌村",
      "投票所": 144,
      "有效票數": 1,
      "無效票數": 0,
      "投票數": 1,
      "已領未投票數": 0,
      "發出票數": 1,
      "用餘票數": 2,
      "選舉人數": 3,
      "投票率": 33.33000183105469,
      "曾智勇": 0,
      "高金素梅": 1,
      "邱文生": 0,
      "孔文吉": 0,
      "瓦歷斯‧貝林 Walis‧Perin": 0,
      "簡東明 Uliw．Qaljupayare": 0
    },
    {
      "區別": "東河鄉",
      "里別": "東河村",
      "投票所": 145,
      "有效票數": 5,
      "無效票數": 0,
      "投票數": 5,
      "已領未投票數": 0,
      "發出票數": 5,
      "用餘票數": 3,
      "選舉人數": 8,
      "投票率": 62.5,
      "曾智勇": 1,
      "高金素梅": 1,
      "邱文生": 0,
      "孔文吉": 1,
      "瓦歷斯‧貝林 Walis‧Perin": 0,
      "簡東明 Uliw．Qaljupayare": 2
    },
    {
      "區別": "東河鄉",
      "里別": "泰源村",
      "投票所": 146,
      "有效票數": 0,
      "無效票數": 0,
      "投票數": 0,
      "已領未投票數": 0,
      "發出票數": 0,
      "用餘票數": 8,
      "選舉人數": 8,
      "投票率": 0,
      "曾智勇": 0,
      "高金素梅": 0,
      "邱文生": 0,
      "孔文吉": 0,
      "瓦歷斯‧貝林 Walis‧Perin": 0,
      "簡東明 Uliw．Qaljupayare": 0
    },
    {
      "區別": "東河鄉",
      "里別": "北源村",
      "投票所": 147,
      "有效票數": 2,
      "無效票數": 0,
      "投票數": 2,
      "已領未投票數": 0,
      "發出票數": 2,
      "用餘票數": 1,
      "選舉人數": 3,
      "投票率": 66.66999816894531,
      "曾智勇": 0,
      "高金素梅": 0,
      "邱文生": 0,
      "孔文吉": 1,
      "瓦歷斯‧貝林 Walis‧Perin": 0,
      "簡東明 Uliw．Qaljupayare": 1
    },
    {
      "區別": "東河鄉",
      "里別": "北源村",
      "投票所": 148,
      "有效票數": 1,
      "無效票數": 0,
      "投票數": 1,
      "已領未投票數": 0,
      "發出票數": 1,
      "用餘票數": 3,
      "選舉人數": 4,
      "投票率": 25,
      "曾智勇": 0,
      "高金素梅": 0,
      "邱文生": 0,
      "孔文吉": 1,
      "瓦歷斯‧貝林 Walis‧Perin": 0,
      "簡東明 Uliw．Qaljupayare": 0
    },
    {
      "區別": "東河鄉",
      "里別": "北源村",
      "投票所": 149,
      "有效票數": 1,
      "無效票數": 0,
      "投票數": 1,
      "已領未投票數": 0,
      "發出票數": 1,
      "用餘票數": 1,
      "選舉人數": 2,
      "投票率": 50,
      "曾智勇": 0,
      "高金素梅": 1,
      "邱文生": 0,
      "孔文吉": 0,
      "瓦歷斯‧貝林 Walis‧Perin": 0,
      "簡東明 Uliw．Qaljupayare": 0
    },
    {
      "區別": "東河鄉",
      "里別": "尚德村",
      "投票所": 150,
      "有效票數": 0,
      "無效票數": 0,
      "投票數": 0,
      "已領未投票數": 0,
      "發出票數": 0,
      "用餘票數": 2,
      "選舉人數": 2,
      "投票率": 0,
      "曾智勇": 0,
      "高金素梅": 0,
      "邱文生": 0,
      "孔文吉": 0,
      "瓦歷斯‧貝林 Walis‧Perin": 0,
      "簡東明 Uliw．Qaljupayare": 0
    },
    {
      "區別": "長濱鄉",
      "里別": "寧埔村",
      "投票所": 151,
      "有效票數": 2,
      "無效票數": 0,
      "投票數": 2,
      "已領未投票數": 0,
      "發出票數": 2,
      "用餘票數": 3,
      "選舉人數": 5,
      "投票率": 40,
      "曾智勇": 1,
      "高金素梅": 0,
      "邱文生": 0,
      "孔文吉": 0,
      "瓦歷斯‧貝林 Walis‧Perin": 0,
      "簡東明 Uliw．Qaljupayare": 1
    },
    {
      "區別": "長濱鄉",
      "里別": "寧埔村",
      "投票所": 152,
      "有效票數": 0,
      "無效票數": 0,
      "投票數": 0,
      "已領未投票數": 0,
      "發出票數": 0,
      "用餘票數": 1,
      "選舉人數": 1,
      "投票率": 0,
      "曾智勇": 0,
      "高金素梅": 0,
      "邱文生": 0,
      "孔文吉": 0,
      "瓦歷斯‧貝林 Walis‧Perin": 0,
      "簡東明 Uliw．Qaljupayare": 0
    },
    {
      "區別": "長濱鄉",
      "里別": "竹湖村",
      "投票所": 153,
      "有效票數": 1,
      "無效票數": 0,
      "投票數": 1,
      "已領未投票數": 0,
      "發出票數": 1,
      "用餘票數": 3,
      "選舉人數": 4,
      "投票率": 25,
      "曾智勇": 0,
      "高金素梅": 0,
      "邱文生": 0,
      "孔文吉": 1,
      "瓦歷斯‧貝林 Walis‧Perin": 0,
      "簡東明 Uliw．Qaljupayare": 0
    },
    {
      "區別": "長濱鄉",
      "里別": "長濱村",
      "投票所": 154,
      "有效票數": 3,
      "無效票數": 1,
      "投票數": 4,
      "已領未投票數": 0,
      "發出票數": 4,
      "用餘票數": 8,
      "選舉人數": 12,
      "投票率": 33.33000183105469,
      "曾智勇": 0,
      "高金素梅": 2,
      "邱文生": 0,
      "孔文吉": 0,
      "瓦歷斯‧貝林 Walis‧Perin": 1,
      "簡東明 Uliw．Qaljupayare": 0
    },
    {
      "區別": "長濱鄉",
      "里別": "長濱村",
      "投票所": 155,
      "有效票數": 0,
      "無效票數": 0,
      "投票數": 0,
      "已領未投票數": 0,
      "發出票數": 0,
      "用餘票數": 2,
      "選舉人數": 2,
      "投票率": 0,
      "曾智勇": 0,
      "高金素梅": 0,
      "邱文生": 0,
      "孔文吉": 0,
      "瓦歷斯‧貝林 Walis‧Perin": 0,
      "簡東明 Uliw．Qaljupayare": 0
    },
    {
      "區別": "長濱鄉",
      "里別": "忠勇村",
      "投票所": 156,
      "有效票數": 2,
      "無效票數": 1,
      "投票數": 3,
      "已領未投票數": 0,
      "發出票數": 3,
      "用餘票數": 10,
      "選舉人數": 13,
      "投票率": 23.079999923706055,
      "曾智勇": 0,
      "高金素梅": 1,
      "邱文生": 0,
      "孔文吉": 0,
      "瓦歷斯‧貝林 Walis‧Perin": 1,
      "簡東明 Uliw．Qaljupayare": 0
    },
    {
      "區別": "長濱鄉",
      "里別": "三間村",
      "投票所": 157,
      "有效票數": 0,
      "無效票數": 0,
      "投票數": 0,
      "已領未投票數": 0,
      "發出票數": 0,
      "用餘票數": 3,
      "選舉人數": 3,
      "投票率": 0,
      "曾智勇": 0,
      "高金素梅": 0,
      "邱文生": 0,
      "孔文吉": 0,
      "瓦歷斯‧貝林 Walis‧Perin": 0,
      "簡東明 Uliw．Qaljupayare": 0
    },
    {
      "區別": "長濱鄉",
      "里別": "三間村",
      "投票所": 158,
      "有效票數": 0,
      "無效票數": 0,
      "投票數": 0,
      "已領未投票數": 0,
      "發出票數": 0,
      "用餘票數": 2,
      "選舉人數": 2,
      "投票率": 0,
      "曾智勇": 0,
      "高金素梅": 0,
      "邱文生": 0,
      "孔文吉": 0,
      "瓦歷斯‧貝林 Walis‧Perin": 0,
      "簡東明 Uliw．Qaljupayare": 0
    },
    {
      "區別": "長濱鄉",
      "里別": "樟原村、三間村",
      "投票所": 159,
      "有效票數": 27,
      "無效票數": 0,
      "投票數": 27,
      "已領未投票數": 0,
      "發出票數": 27,
      "用餘票數": 42,
      "選舉人數": 69,
      "投票率": 39.130001068115234,
      "曾智勇": 1,
      "高金素梅": 5,
      "邱文生": 1,
      "孔文吉": 11,
      "瓦歷斯‧貝林 Walis‧Perin": 8,
      "簡東明 Uliw．Qaljupayare": 1
    },
    {
      "區別": "長濱鄉",
      "里別": "樟原村",
      "投票所": 160,
      "有效票數": 5,
      "無效票數": 0,
      "投票數": 5,
      "已領未投票數": 0,
      "發出票數": 5,
      "用餘票數": 3,
      "選舉人數": 8,
      "投票率": 62.5,
      "曾智勇": 0,
      "高金素梅": 0,
      "邱文生": 0,
      "孔文吉": 4,
      "瓦歷斯‧貝林 Walis‧Perin": 1,
      "簡東明 Uliw．Qaljupayare": 0
    },
    {
      "區別": "太麻里鄉",
      "里別": "美和村",
      "投票所": 161,
      "有效票數": 3,
      "無效票數": 0,
      "投票數": 3,
      "已領未投票數": 0,
      "發出票數": 3,
      "用餘票數": 2,
      "選舉人數": 5,
      "投票率": 60,
      "曾智勇": 0,
      "高金素梅": 0,
      "邱文生": 0,
      "孔文吉": 3,
      "瓦歷斯‧貝林 Walis‧Perin": 0,
      "簡東明 Uliw．Qaljupayare": 0
    },
    {
      "區別": "太麻里鄉",
      "里別": "美和村",
      "投票所": 162,
      "有效票數": 6,
      "無效票數": 0,
      "投票數": 6,
      "已領未投票數": 0,
      "發出票數": 6,
      "用餘票數": 4,
      "選舉人數": 10,
      "投票率": 60,
      "曾智勇": 0,
      "高金素梅": 3,
      "邱文生": 0,
      "孔文吉": 0,
      "瓦歷斯‧貝林 Walis‧Perin": 0,
      "簡東明 Uliw．Qaljupayare": 3
    },
    {
      "區別": "太麻里鄉",
      "里別": "三和村",
      "投票所": 163,
      "有效票數": 2,
      "無效票數": 0,
      "投票數": 2,
      "已領未投票數": 0,
      "發出票數": 2,
      "用餘票數": 1,
      "選舉人數": 3,
      "投票率": 66.66999816894531,
      "曾智勇": 0,
      "高金素梅": 1,
      "邱文生": 0,
      "孔文吉": 0,
      "瓦歷斯‧貝林 Walis‧Perin": 1,
      "簡東明 Uliw．Qaljupayare": 0
    },
    {
      "區別": "太麻里鄉",
      "里別": "華源村",
      "投票所": 164,
      "有效票數": 5,
      "無效票數": 0,
      "投票數": 5,
      "已領未投票數": 0,
      "發出票數": 5,
      "用餘票數": 1,
      "選舉人數": 6,
      "投票率": 83.33000183105469,
      "曾智勇": 0,
      "高金素梅": 2,
      "邱文生": 0,
      "孔文吉": 0,
      "瓦歷斯‧貝林 Walis‧Perin": 0,
      "簡東明 Uliw．Qaljupayare": 3
    },
    {
      "區別": "太麻里鄉",
      "里別": "北里村",
      "投票所": 165,
      "有效票數": 7,
      "無效票數": 0,
      "投票數": 7,
      "已領未投票數": 0,
      "發出票數": 7,
      "用餘票數": 3,
      "選舉人數": 10,
      "投票率": 70,
      "曾智勇": 1,
      "高金素梅": 3,
      "邱文生": 0,
      "孔文吉": 0,
      "瓦歷斯‧貝林 Walis‧Perin": 0,
      "簡東明 Uliw．Qaljupayare": 3
    },
    {
      "區別": "太麻里鄉",
      "里別": "大王村",
      "投票所": 166,
      "有效票數": 42,
      "無效票數": 0,
      "投票數": 42,
      "已領未投票數": 0,
      "發出票數": 42,
      "用餘票數": 23,
      "選舉人數": 65,
      "投票率": 64.62000274658203,
      "曾智勇": 1,
      "高金素梅": 9,
      "邱文生": 0,
      "孔文吉": 9,
      "瓦歷斯‧貝林 Walis‧Perin": 3,
      "簡東明 Uliw．Qaljupayare": 20
    },
    {
      "區別": "太麻里鄉",
      "里別": "大王村",
      "投票所": 167,
      "有效票數": 9,
      "無效票數": 0,
      "投票數": 9,
      "已領未投票數": 0,
      "發出票數": 9,
      "用餘票數": 7,
      "選舉人數": 16,
      "投票率": 56.25,
      "曾智勇": 2,
      "高金素梅": 1,
      "邱文生": 0,
      "孔文吉": 2,
      "瓦歷斯‧貝林 Walis‧Perin": 2,
      "簡東明 Uliw．Qaljupayare": 2
    },
    {
      "區別": "太麻里鄉",
      "里別": "泰和村",
      "投票所": 168,
      "有效票數": 13,
      "無效票數": 0,
      "投票數": 13,
      "已領未投票數": 0,
      "發出票數": 13,
      "用餘票數": 7,
      "選舉人數": 20,
      "投票率": 65,
      "曾智勇": 4,
      "高金素梅": 3,
      "邱文生": 0,
      "孔文吉": 2,
      "瓦歷斯‧貝林 Walis‧Perin": 1,
      "簡東明 Uliw．Qaljupayare": 3
    },
    {
      "區別": "太麻里鄉",
      "里別": "泰和村",
      "投票所": 169,
      "有效票數": 10,
      "無效票數": 0,
      "投票數": 10,
      "已領未投票數": 0,
      "發出票數": 10,
      "用餘票數": 5,
      "選舉人數": 15,
      "投票率": 66.66999816894531,
      "曾智勇": 2,
      "高金素梅": 1,
      "邱文生": 0,
      "孔文吉": 0,
      "瓦歷斯‧貝林 Walis‧Perin": 3,
      "簡東明 Uliw．Qaljupayare": 4
    },
    {
      "區別": "太麻里鄉",
      "里別": "香蘭村",
      "投票所": 170,
      "有效票數": 4,
      "無效票數": 1,
      "投票數": 5,
      "已領未投票數": 0,
      "發出票數": 5,
      "用餘票數": 2,
      "選舉人數": 7,
      "投票率": 71.43000030517578,
      "曾智勇": 0,
      "高金素梅": 0,
      "邱文生": 0,
      "孔文吉": 1,
      "瓦歷斯‧貝林 Walis‧Perin": 0,
      "簡東明 Uliw．Qaljupayare": 3
    },
    {
      "區別": "太麻里鄉",
      "里別": "香蘭村",
      "投票所": 171,
      "有效票數": 5,
      "無效票數": 1,
      "投票數": 6,
      "已領未投票數": 0,
      "發出票數": 6,
      "用餘票數": 2,
      "選舉人數": 8,
      "投票率": 75,
      "曾智勇": 2,
      "高金素梅": 2,
      "邱文生": 0,
      "孔文吉": 0,
      "瓦歷斯‧貝林 Walis‧Perin": 0,
      "簡東明 Uliw．Qaljupayare": 1
    },
    {
      "區別": "太麻里鄉",
      "里別": "金崙村",
      "投票所": 172,
      "有效票數": 41,
      "無效票數": 1,
      "投票數": 42,
      "已領未投票數": 0,
      "發出票數": 42,
      "用餘票數": 20,
      "選舉人數": 62,
      "投票率": 67.73999786376953,
      "曾智勇": 2,
      "高金素梅": 14,
      "邱文生": 1,
      "孔文吉": 4,
      "瓦歷斯‧貝林 Walis‧Perin": 2,
      "簡東明 Uliw．Qaljupayare": 18
    },
    {
      "區別": "太麻里鄉",
      "里別": "金崙村",
      "投票所": 173,
      "有效票數": 31,
      "無效票數": 0,
      "投票數": 31,
      "已領未投票數": 0,
      "發出票數": 31,
      "用餘票數": 20,
      "選舉人數": 51,
      "投票率": 60.779998779296875,
      "曾智勇": 2,
      "高金素梅": 2,
      "邱文生": 0,
      "孔文吉": 4,
      "瓦歷斯‧貝林 Walis‧Perin": 4,
      "簡東明 Uliw．Qaljupayare": 19
    },
    {
      "區別": "太麻里鄉",
      "里別": "多良村",
      "投票所": 174,
      "有效票數": 4,
      "無效票數": 0,
      "投票數": 4,
      "已領未投票數": 0,
      "發出票數": 4,
      "用餘票數": 1,
      "選舉人數": 5,
      "投票率": 80,
      "曾智勇": 0,
      "高金素梅": 0,
      "邱文生": 0,
      "孔文吉": 0,
      "瓦歷斯‧貝林 Walis‧Perin": 0,
      "簡東明 Uliw．Qaljupayare": 4
    },
    {
      "區別": "太麻里鄉",
      "里別": "多良村",
      "投票所": 175,
      "有效票數": 36,
      "無效票數": 1,
      "投票數": 37,
      "已領未投票數": 0,
      "發出票數": 37,
      "用餘票數": 24,
      "選舉人數": 61,
      "投票率": 60.65999984741211,
      "曾智勇": 0,
      "高金素梅": 7,
      "邱文生": 0,
      "孔文吉": 7,
      "瓦歷斯‧貝林 Walis‧Perin": 4,
      "簡東明 Uliw．Qaljupayare": 18
    },
    {
      "區別": "大武鄉",
      "里別": "南興村",
      "投票所": 176,
      "有效票數": 19,
      "無效票數": 0,
      "投票數": 19,
      "已領未投票數": 0,
      "發出票數": 19,
      "用餘票數": 30,
      "選舉人數": 49,
      "投票率": 38.779998779296875,
      "曾智勇": 1,
      "高金素梅": 3,
      "邱文生": 0,
      "孔文吉": 1,
      "瓦歷斯‧貝林 Walis‧Perin": 0,
      "簡東明 Uliw．Qaljupayare": 14
    },
    {
      "區別": "大武鄉",
      "里別": "尚武村",
      "投票所": 177,
      "有效票數": 28,
      "無效票數": 1,
      "投票數": 29,
      "已領未投票數": 0,
      "發出票數": 29,
      "用餘票數": 34,
      "選舉人數": 63,
      "投票率": 46.029998779296875,
      "曾智勇": 1,
      "高金素梅": 7,
      "邱文生": 0,
      "孔文吉": 3,
      "瓦歷斯‧貝林 Walis‧Perin": 8,
      "簡東明 Uliw．Qaljupayare": 9
    },
    {
      "區別": "大武鄉",
      "里別": "大武村",
      "投票所": 178,
      "有效票數": 54,
      "無效票數": 1,
      "投票數": 55,
      "已領未投票數": 0,
      "發出票數": 55,
      "用餘票數": 53,
      "選舉人數": 108,
      "投票率": 50.93000030517578,
      "曾智勇": 3,
      "高金素梅": 10,
      "邱文生": 1,
      "孔文吉": 6,
      "瓦歷斯‧貝林 Walis‧Perin": 7,
      "簡東明 Uliw．Qaljupayare": 27
    },
    {
      "區別": "大武鄉",
      "里別": "大鳥村",
      "投票所": 179,
      "有效票數": 25,
      "無效票數": 0,
      "投票數": 25,
      "已領未投票數": 0,
      "發出票數": 25,
      "用餘票數": 18,
      "選舉人數": 43,
      "投票率": 58.13999938964844,
      "曾智勇": 1,
      "高金素梅": 2,
      "邱文生": 0,
      "孔文吉": 0,
      "瓦歷斯‧貝林 Walis‧Perin": 3,
      "簡東明 Uliw．Qaljupayare": 19
    },
    {
      "區別": "大武鄉",
      "里別": "大竹村",
      "投票所": 180,
      "有效票數": 7,
      "無效票數": 0,
      "投票數": 7,
      "已領未投票數": 0,
      "發出票數": 7,
      "用餘票數": 8,
      "選舉人數": 15,
      "投票率": 46.66999816894531,
      "曾智勇": 0,
      "高金素梅": 2,
      "邱文生": 0,
      "孔文吉": 1,
      "瓦歷斯‧貝林 Walis‧Perin": 0,
      "簡東明 Uliw．Qaljupayare": 4
    },
    {
      "區別": "大武鄉",
      "里別": "大竹村",
      "投票所": 181,
      "有效票數": 17,
      "無效票數": 0,
      "投票數": 17,
      "已領未投票數": 0,
      "發出票數": 17,
      "用餘票數": 12,
      "選舉人數": 29,
      "投票率": 58.619998931884766,
      "曾智勇": 2,
      "高金素梅": 4,
      "邱文生": 0,
      "孔文吉": 8,
      "瓦歷斯‧貝林 Walis‧Perin": 0,
      "簡東明 Uliw．Qaljupayare": 3
    },
    {
      "區別": "綠島鄉",
      "里別": "南寮村",
      "投票所": 182,
      "有效票數": 2,
      "無效票數": 0,
      "投票數": 2,
      "已領未投票數": 0,
      "發出票數": 2,
      "用餘票數": 1,
      "選舉人數": 3,
      "投票率": 66.66999816894531,
      "曾智勇": 0,
      "高金素梅": 1,
      "邱文生": 0,
      "孔文吉": 1,
      "瓦歷斯‧貝林 Walis‧Perin": 0,
      "簡東明 Uliw．Qaljupayare": 0
    },
    {
      "區別": "綠島鄉",
      "里別": "中寮村",
      "投票所": 183,
      "有效票數": 1,
      "無效票數": 0,
      "投票數": 1,
      "已領未投票數": 0,
      "發出票數": 1,
      "用餘票數": 1,
      "選舉人數": 2,
      "投票率": 50,
      "曾智勇": 0,
      "高金素梅": 0,
      "邱文生": 0,
      "孔文吉": 0,
      "瓦歷斯‧貝林 Walis‧Perin": 0,
      "簡東明 Uliw．Qaljupayare": 1
    },
    {
      "區別": "綠島鄉",
      "里別": "公村",
      "投票所": 184,
      "有效票數": 3,
      "無效票數": 0,
      "投票數": 3,
      "已領未投票數": 0,
      "發出票數": 3,
      "用餘票數": 0,
      "選舉人數": 3,
      "投票率": 100,
      "曾智勇": 0,
      "高金素梅": 1,
      "邱文生": 0,
      "孔文吉": 1,
      "瓦歷斯‧貝林 Walis‧Perin": 1,
      "簡東明 Uliw．Qaljupayare": 0
    },
    {
      "區別": "綠島鄉",
      "里別": "公村",
      "投票所": 185,
      "有效票數": 0,
      "無效票數": 0,
      "投票數": 0,
      "已領未投票數": 0,
      "發出票數": 0,
      "用餘票數": 0,
      "選舉人數": 0,
      "投票率": 0,
      "曾智勇": 0,
      "高金素梅": 0,
      "邱文生": 0,
      "孔文吉": 0,
      "瓦歷斯‧貝林 Walis‧Perin": 0,
      "簡東明 Uliw．Qaljupayare": 0
    },
    {
      "區別": "海端鄉",
      "里別": "加拿村",
      "投票所": 186,
      "有效票數": 228,
      "無效票數": 5,
      "投票數": 233,
      "已領未投票數": 0,
      "發出票數": 233,
      "用餘票數": 218,
      "選舉人數": 451,
      "投票率": 51.65999984741211,
      "曾智勇": 8,
      "高金素梅": 38,
      "邱文生": 2,
      "孔文吉": 87,
      "瓦歷斯‧貝林 Walis‧Perin": 17,
      "簡東明 Uliw．Qaljupayare": 76
    },
    {
      "區別": "海端鄉",
      "里別": "崁頂村",
      "投票所": 187,
      "有效票數": 266,
      "無效票數": 7,
      "投票數": 273,
      "已領未投票數": 0,
      "發出票數": 273,
      "用餘票數": 219,
      "選舉人數": 492,
      "投票率": 55.4900016784668,
      "曾智勇": 12,
      "高金素梅": 42,
      "邱文生": 2,
      "孔文吉": 124,
      "瓦歷斯‧貝林 Walis‧Perin": 41,
      "簡東明 Uliw．Qaljupayare": 45
    },
    {
      "區別": "海端鄉",
      "里別": "海端村",
      "投票所": 188,
      "有效票數": 407,
      "無效票數": 13,
      "投票數": 420,
      "已領未投票數": 0,
      "發出票數": 420,
      "用餘票數": 367,
      "選舉人數": 787,
      "投票率": 53.369998931884766,
      "曾智勇": 23,
      "高金素梅": 48,
      "邱文生": 6,
      "孔文吉": 168,
      "瓦歷斯‧貝林 Walis‧Perin": 55,
      "簡東明 Uliw．Qaljupayare": 107
    },
    {
      "區別": "海端鄉",
      "里別": "廣原村",
      "投票所": 189,
      "有效票數": 329,
      "無效票數": 6,
      "投票數": 335,
      "已領未投票數": 0,
      "發出票數": 335,
      "用餘票數": 295,
      "選舉人數": 630,
      "投票率": 53.16999816894531,
      "曾智勇": 9,
      "高金素梅": 55,
      "邱文生": 2,
      "孔文吉": 126,
      "瓦歷斯‧貝林 Walis‧Perin": 20,
      "簡東明 Uliw．Qaljupayare": 117
    },
    {
      "區別": "海端鄉",
      "里別": "霧鹿村",
      "投票所": 190,
      "有效票數": 142,
      "無效票數": 2,
      "投票數": 144,
      "已領未投票數": 0,
      "發出票數": 144,
      "用餘票數": 99,
      "選舉人數": 243,
      "投票率": 59.2599983215332,
      "曾智勇": 2,
      "高金素梅": 14,
      "邱文生": 3,
      "孔文吉": 94,
      "瓦歷斯‧貝林 Walis‧Perin": 17,
      "簡東明 Uliw．Qaljupayare": 12
    },
    {
      "區別": "海端鄉",
      "里別": "利稻村",
      "投票所": 191,
      "有效票數": 109,
      "無效票數": 5,
      "投票數": 114,
      "已領未投票數": 0,
      "發出票數": 114,
      "用餘票數": 97,
      "選舉人數": 211,
      "投票率": 54.029998779296875,
      "曾智勇": 7,
      "高金素梅": 26,
      "邱文生": 1,
      "孔文吉": 31,
      "瓦歷斯‧貝林 Walis‧Perin": 23,
      "簡東明 Uliw．Qaljupayare": 21
    },
    {
      "區別": "延平鄉",
      "里別": "桃源村",
      "投票所": 192,
      "有效票數": 425,
      "無效票數": 13,
      "投票數": 438,
      "已領未投票數": 0,
      "發出票數": 438,
      "用餘票數": 310,
      "選舉人數": 748,
      "投票率": 58.560001373291016,
      "曾智勇": 53,
      "高金素梅": 26,
      "邱文生": 2,
      "孔文吉": 242,
      "瓦歷斯‧貝林 Walis‧Perin": 48,
      "簡東明 Uliw．Qaljupayare": 54
    },
    {
      "區別": "延平鄉",
      "里別": "紅葉村",
      "投票所": 193,
      "有效票數": 173,
      "無效票數": 8,
      "投票數": 181,
      "已領未投票數": 0,
      "發出票數": 181,
      "用餘票數": 167,
      "選舉人數": 348,
      "投票率": 52.0099983215332,
      "曾智勇": 5,
      "高金素梅": 13,
      "邱文生": 2,
      "孔文吉": 110,
      "瓦歷斯‧貝林 Walis‧Perin": 17,
      "簡東明 Uliw．Qaljupayare": 26
    },
    {
      "區別": "延平鄉",
      "里別": "永康村",
      "投票所": 194,
      "有效票數": 146,
      "無效票數": 5,
      "投票數": 151,
      "已領未投票數": 0,
      "發出票數": 151,
      "用餘票數": 84,
      "選舉人數": 235,
      "投票率": 64.26000213623047,
      "曾智勇": 3,
      "高金素梅": 4,
      "邱文生": 1,
      "孔文吉": 99,
      "瓦歷斯‧貝林 Walis‧Perin": 11,
      "簡東明 Uliw．Qaljupayare": 28
    },
    {
      "區別": "延平鄉",
      "里別": "武陵村",
      "投票所": 195,
      "有效票數": 284,
      "無效票數": 14,
      "投票數": 298,
      "已領未投票數": 0,
      "發出票數": 298,
      "用餘票數": 213,
      "選舉人數": 511,
      "投票率": 58.31999969482422,
      "曾智勇": 8,
      "高金素梅": 18,
      "邱文生": 0,
      "孔文吉": 178,
      "瓦歷斯‧貝林 Walis‧Perin": 28,
      "簡東明 Uliw．Qaljupayare": 52
    },
    {
      "區別": "延平鄉",
      "里別": "鸞山村",
      "投票所": 196,
      "有效票數": 244,
      "無效票數": 13,
      "投票數": 257,
      "已領未投票數": 0,
      "發出票數": 257,
      "用餘票數": 184,
      "選舉人數": 441,
      "投票率": 58.279998779296875,
      "曾智勇": 6,
      "高金素梅": 34,
      "邱文生": 1,
      "孔文吉": 109,
      "瓦歷斯‧貝林 Walis‧Perin": 52,
      "簡東明 Uliw．Qaljupayare": 42
    },
    {
      "區別": "金峰鄉",
      "里別": "嘉蘭村",
      "投票所": 197,
      "有效票數": 639,
      "無效票數": 8,
      "投票數": 647,
      "已領未投票數": 0,
      "發出票數": 647,
      "用餘票數": 333,
      "選舉人數": 980,
      "投票率": 66.0199966430664,
      "曾智勇": 29,
      "高金素梅": 145,
      "邱文生": 4,
      "孔文吉": 166,
      "瓦歷斯‧貝林 Walis‧Perin": 88,
      "簡東明 Uliw．Qaljupayare": 207
    },
    {
      "區別": "金峰鄉",
      "里別": "正興村",
      "投票所": 198,
      "有效票數": 296,
      "無效票數": 2,
      "投票數": 298,
      "已領未投票數": 0,
      "發出票數": 298,
      "用餘票數": 117,
      "選舉人數": 415,
      "投票率": 71.80999755859375,
      "曾智勇": 12,
      "高金素梅": 96,
      "邱文生": 2,
      "孔文吉": 13,
      "瓦歷斯‧貝林 Walis‧Perin": 25,
      "簡東明 Uliw．Qaljupayare": 148
    },
    {
      "區別": "金峰鄉",
      "里別": "新興村",
      "投票所": 199,
      "有效票數": 247,
      "無效票數": 1,
      "投票數": 248,
      "已領未投票數": 0,
      "發出票數": 248,
      "用餘票數": 110,
      "選舉人數": 358,
      "投票率": 69.2699966430664,
      "曾智勇": 24,
      "高金素梅": 37,
      "邱文生": 0,
      "孔文吉": 13,
      "瓦歷斯‧貝林 Walis‧Perin": 46,
      "簡東明 Uliw．Qaljupayare": 127
    },
    {
      "區別": "金峰鄉",
      "里別": "賓茂村",
      "投票所": 200,
      "有效票數": 180,
      "無效票數": 5,
      "投票數": 185,
      "已領未投票數": 0,
      "發出票數": 185,
      "用餘票數": 88,
      "選舉人數": 273,
      "投票率": 67.7699966430664,
      "曾智勇": 28,
      "高金素梅": 26,
      "邱文生": 1,
      "孔文吉": 8,
      "瓦歷斯‧貝林 Walis‧Perin": 6,
      "簡東明 Uliw．Qaljupayare": 111
    },
    {
      "區別": "金峰鄉",
      "里別": "歷坵村",
      "投票所": 201,
      "有效票數": 177,
      "無效票數": 6,
      "投票數": 183,
      "已領未投票數": 0,
      "發出票數": 183,
      "用餘票數": 94,
      "選舉人數": 277,
      "投票率": 66.05999755859375,
      "曾智勇": 5,
      "高金素梅": 16,
      "邱文生": 0,
      "孔文吉": 6,
      "瓦歷斯‧貝林 Walis‧Perin": 4,
      "簡東明 Uliw．Qaljupayare": 146
    },
    {
      "區別": "達仁鄉",
      "里別": "安朔村",
      "投票所": 202,
      "有效票數": 114,
      "無效票數": 0,
      "投票數": 114,
      "已領未投票數": 0,
      "發出票數": 114,
      "用餘票數": 57,
      "選舉人數": 171,
      "投票率": 66.66999816894531,
      "曾智勇": 7,
      "高金素梅": 16,
      "邱文生": 0,
      "孔文吉": 6,
      "瓦歷斯‧貝林 Walis‧Perin": 14,
      "簡東明 Uliw．Qaljupayare": 71
    },
    {
      "區別": "達仁鄉",
      "里別": "安朔村",
      "投票所": 203,
      "有效票數": 156,
      "無效票數": 6,
      "投票數": 162,
      "已領未投票數": 0,
      "發出票數": 162,
      "用餘票數": 151,
      "選舉人數": 313,
      "投票率": 51.7599983215332,
      "曾智勇": 14,
      "高金素梅": 34,
      "邱文生": 0,
      "孔文吉": 11,
      "瓦歷斯‧貝林 Walis‧Perin": 6,
      "簡東明 Uliw．Qaljupayare": 91
    },
    {
      "區別": "達仁鄉",
      "里別": "南田村",
      "投票所": 204,
      "有效票數": 128,
      "無效票數": 5,
      "投票數": 133,
      "已領未投票數": 0,
      "發出票數": 133,
      "用餘票數": 94,
      "選舉人數": 227,
      "投票率": 58.59000015258789,
      "曾智勇": 9,
      "高金素梅": 20,
      "邱文生": 0,
      "孔文吉": 1,
      "瓦歷斯‧貝林 Walis‧Perin": 15,
      "簡東明 Uliw．Qaljupayare": 83
    },
    {
      "區別": "達仁鄉",
      "里別": "森永村",
      "投票所": 205,
      "有效票數": 190,
      "無效票數": 5,
      "投票數": 195,
      "已領未投票數": 0,
      "發出票數": 195,
      "用餘票數": 140,
      "選舉人數": 335,
      "投票率": 58.209999084472656,
      "曾智勇": 19,
      "高金素梅": 17,
      "邱文生": 1,
      "孔文吉": 13,
      "瓦歷斯‧貝林 Walis‧Perin": 33,
      "簡東明 Uliw．Qaljupayare": 107
    },
    {
      "區別": "達仁鄉",
      "里別": "新化村",
      "投票所": 206,
      "有效票數": 169,
      "無效票數": 3,
      "投票數": 172,
      "已領未投票數": 0,
      "發出票數": 172,
      "用餘票數": 127,
      "選舉人數": 299,
      "投票率": 57.529998779296875,
      "曾智勇": 12,
      "高金素梅": 15,
      "邱文生": 0,
      "孔文吉": 18,
      "瓦歷斯‧貝林 Walis‧Perin": 16,
      "簡東明 Uliw．Qaljupayare": 108
    },
    {
      "區別": "達仁鄉",
      "里別": "台村",
      "投票所": 207,
      "有效票數": 350,
      "無效票數": 6,
      "投票數": 356,
      "已領未投票數": 0,
      "發出票數": 356,
      "用餘票數": 214,
      "選舉人數": 570,
      "投票率": 62.459999084472656,
      "曾智勇": 5,
      "高金素梅": 73,
      "邱文生": 2,
      "孔文吉": 51,
      "瓦歷斯‧貝林 Walis‧Perin": 20,
      "簡東明 Uliw．Qaljupayare": 199
    },
    {
      "區別": "達仁鄉",
      "里別": "土村",
      "投票所": 208,
      "有效票數": 402,
      "無效票數": 8,
      "投票數": 410,
      "已領未投票數": 0,
      "發出票數": 410,
      "用餘票數": 365,
      "選舉人數": 775,
      "投票率": 52.900001525878906,
      "曾智勇": 10,
      "高金素梅": 53,
      "邱文生": 2,
      "孔文吉": 24,
      "瓦歷斯‧貝林 Walis‧Perin": 94,
      "簡東明 Uliw．Qaljupayare": 219
    },
    {
      "區別": "蘭嶼鄉",
      "里別": "椰油村",
      "投票所": 209,
      "有效票數": 220,
      "無效票數": 25,
      "投票數": 245,
      "已領未投票數": 0,
      "發出票數": 245,
      "用餘票數": 308,
      "選舉人數": 553,
      "投票率": 44.29999923706055,
      "曾智勇": 3,
      "高金素梅": 93,
      "邱文生": 7,
      "孔文吉": 21,
      "瓦歷斯‧貝林 Walis‧Perin": 31,
      "簡東明 Uliw．Qaljupayare": 65
    },
    {
      "區別": "蘭嶼鄉",
      "里別": "紅頭村",
      "投票所": 210,
      "有效票數": 291,
      "無效票數": 30,
      "投票數": 321,
      "已領未投票數": 0,
      "發出票數": 321,
      "用餘票數": 437,
      "選舉人數": 758,
      "投票率": 42.349998474121094,
      "曾智勇": 21,
      "高金素梅": 101,
      "邱文生": 3,
      "孔文吉": 54,
      "瓦歷斯‧貝林 Walis‧Perin": 59,
      "簡東明 Uliw．Qaljupayare": 53
    },
    {
      "區別": "蘭嶼鄉",
      "里別": "東清村",
      "投票所": 211,
      "有效票數": 370,
      "無效票數": 20,
      "投票數": 390,
      "已領未投票數": 0,
      "發出票數": 390,
      "用餘票數": 488,
      "選舉人數": 878,
      "投票率": 44.41999816894531,
      "曾智勇": 20,
      "高金素梅": 175,
      "邱文生": 3,
      "孔文吉": 18,
      "瓦歷斯‧貝林 Walis‧Perin": 26,
      "簡東明 Uliw．Qaljupayare": 128
    },
    {
      "區別": "蘭嶼鄉",
      "里別": "朗島村",
      "投票所": 212,
      "有效票數": 207,
      "無效票數": 21,
      "投票數": 228,
      "已領未投票數": 0,
      "發出票數": 228,
      "用餘票數": 323,
      "選舉人數": 551,
      "投票率": 41.380001068115234,
      "曾智勇": 11,
      "高金素梅": 79,
      "邱文生": 1,
      "孔文吉": 11,
      "瓦歷斯‧貝林 Walis‧Perin": 58,
      "簡東明 Uliw．Qaljupayare": 47
    }
  ]
}